sim/slave_tester.v
`timescale 1ns / 1ps

module tester (
    input  wire        CLK,
    output reg         RST,
    output reg  [6:0]  I2C_ADDR,
    output reg  [15:0] RD_DATA,
    output reg         SCL,
    output reg         SDA_OUT,
    output reg         SDA_OE,
    input  wire        SDA_IN,
    input  wire [15:0] WR_DATA
);

    // Helper task to handle an I2C Bit stream transmission
    task send_i2c_bit(input bit_val);
        begin
            SDA_OUT = bit_val;
            #40 SCL = 1; // Pull SCL High
            #40 SCL = 0; // Pull SCL Low
        end
    endtask

    initial begin
        // --- Step 1: Initialization & Reset ---
        RST      = 0;  // Trigger active-low reset
        I2C_ADDR = 7'h5A; // Configure the Receiver module's target address
        RD_DATA  = 16'hABCD;
        SCL      = 1;
        SDA_OUT  = 1;
        SDA_OE   = 1;
        
        #40;
        RST      = 1;  // Release reset, normal operation active
        #20;

        $display("At time %0t: --- Starting I2C Receiver Test Environment ---", $time);
        $monitor("At time %0t: SDA_IN (ACK from Receiver) = %b | WR_DATA = %h", $time, SDA_IN, WR_DATA);

        // --- Step 2: Send I2C START Condition ---
        #20;
        SDA_OUT = 0; 
        #20;
        SCL = 0;     
        #20;

        // --- Step 3: Send Matching 7-bit Address (7'h5A -> binary 1011010) ---
        send_i2c_bit(1); // Bit 6
        send_i2c_bit(0); // Bit 5
        send_i2c_bit(1); // Bit 4
        send_i2c_bit(1); // Bit 3
        send_i2c_bit(0); // Bit 2
        send_i2c_bit(1); // Bit 1
        send_i2c_bit(0); // Bit 0

        // --- Step 4: Send the Write Bit (0 = Write) ---
        send_i2c_bit(0); 

        // --- Step 5: Wait for ACK Phase ---
        SDA_OUT = 1; 
        #40 SCL = 1;
        #20;
        
        if (SDA_IN == 0) begin
            $display("At time %0t: SUCCESS - Device generated an ACK for matching Address!", $time);
        end else begin
            $display("At time %0t: WARNING - Device did not ACK address match.", $time);
        end
        
        #20 SCL = 0;

        // ====================================================================
        // --- Step 6: Send Data Byte to Receiver (e.g., 8'hA5 -> 10100101) ---
        // ====================================================================
        $display("At time %0t: --- Sending Data Byte: 8'hA5 ---", $time);
        
        // We will transmit the byte 8'hA5 (MSB first: 1, 0, 1, 0, 0, 1, 0, 1)
        send_i2c_bit(1); // Bit 7
        send_i2c_bit(0); // Bit 6
        send_i2c_bit(1); // Bit 5
        send_i2c_bit(0); // Bit 4
        send_i2c_bit(0); // Bit 3
        send_i2c_bit(1); // Bit 2
        send_i2c_bit(0); // Bit 1
        send_i2c_bit(1); // Bit 0

        // --- Step 7: Wait for Data ACK Phase ---
        SDA_OUT = 1;      // Release the SDA line so the receiver can drive it
        #40 SCL = 1;      // Pull SCL High to sample the ACK
        #20;
        
        if (SDA_IN == 0) begin
            $display("At time %0t: SUCCESS - Device generated an ACK for the Data Byte!", $time);
        end else begin
            $display("At time %0t: WARNING - Device did not ACK the Data Byte.", $time);
        end        
        #20;
        SCL = 0;
        
        $display("At time %0t: --- Sending Data Byte: 8'hE7 ---", $time);
        
        // We will transmit the byte 8'hE7 (MSB first: 1, 1, 1, 0, 0, 1, 1, 1)
        send_i2c_bit(1); // Bit 7
        send_i2c_bit(1); // Bit 6
        send_i2c_bit(1); // Bit 5
        send_i2c_bit(0); // Bit 4
        send_i2c_bit(0); // Bit 3
        send_i2c_bit(1); // Bit 2
        send_i2c_bit(1); // Bit 1
        send_i2c_bit(1); // Bit 0

        // --- Step 7: Wait for Data ACK Phase ---
        SDA_OUT = 1;      // Release the SDA line so the receiver can drive it
        #40 SCL = 1;      // Pull SCL High to sample the ACK
        #20;
        
        if (SDA_IN == 0) begin
            $display("At time %0t: SUCCESS - Device generated an ACK for the Data Byte!", $time);
        end else begin
            $display("At time %0t: WARNING - Device did not ACK the Data Byte.", $time);
        end
        
        #20 SCL = 0;      // Pull SCL Low to finalize the bit cycle
        #40;

        // --- Step 8: Send I2C STOP Condition ---
        SDA_OUT = 0;      // Ensure SDA is low while SCL is low
        #20;
        SCL = 1;          // Pull SCL High
        #20;
        SDA_OUT = 1;      // Transition SDA Low -> High while SCL is High (STOP)
        #40;



        #100;



        $display("At time %0t: --- Starting I2C Receiver Test Environment ---", $time);
        $monitor("At time %0t: SDA_IN (ACK from Receiver) = %b | WR_DATA = %h", $time, SDA_IN, WR_DATA);

        // --- Step 2: Send I2C START Condition ---
        #20;
        SDA_OUT = 0; 
        #20;
        SCL = 0;     
        #20;

        // --- Step 3: Send Matching 7-bit Address (7'h5A -> binary 1011010) ---
        send_i2c_bit(1); // Bit 6
        send_i2c_bit(0); // Bit 5
        send_i2c_bit(1); // Bit 4
        send_i2c_bit(1); // Bit 3
        send_i2c_bit(0); // Bit 2
        send_i2c_bit(1); // Bit 1
        send_i2c_bit(0); // Bit 0

        // --- Step 4: Send the Write Bit (1 = Read) ---
        send_i2c_bit(1); 

        // --- Step 5: Wait for ACK Phase ---
        SDA_OUT = 1; 
        #40 SCL = 1;
        #20;
        
        if (SDA_IN == 0) begin
            $display("At time %0t: SUCCESS - Device generated an ACK for matching Address!", $time);
        end else begin
            $display("At time %0t: WARNING - Device did not ACK address match.", $time);
        end
        
        #20 SCL = 0;


// --- Step 6: Receive a Byte from the Receiver Module ---
        $display("At time %0t: --- Starting Byte Reception ---", $time);
        


        // 2. Clock in 8 bits of data (MSB first)
        // We'll use a small loop to read all 8 bits from SDA_IN
        begin: rx_byte_loop
            integer i;
            reg [7:0] rx_byte;
            
            rx_byte = 8'b0;
            
            for (i = 7; i >= 0; i = i - 1) begin
                #40 SCL = 1;          // Pull SCL High
                #20;                  // Wait for data to stabilize
                rx_byte[i] = SDA_IN;  // Sample the bit
                #20;                  // Complete the high period
                SCL = 0;              // Pull SCL Low
            end
            
            $display("At time %0t: SUCCESS - Received Byte: 8'h%h (8'b%b)", $time, rx_byte, rx_byte);
        end

        // --- Step 7: Send NACK to the Receiver (Master signals end of read) ---

        SDA_OUT = 1;   // 1 = NACK (0 would be ACK)
        #20;
        
        #40 SCL = 1;   // Clock the NACK bit
        #40 SCL = 0;
        #20;






        #100;
        // Finish up simulation
        $display("At time %0t: --- Test Script Execution Complete ---", $time);
        $finish;
    end

endmodule

src/i2c_receiver.v
module i2c_receiver (
    input          CLK,
    input          RST,      // RST=1 normal funstion, 0 restart

    // Interfaz con el CPU
    input   [6:0]  I2C_ADDR,
    output reg [15:0] WR_DATA, // write data to cpu from I2C
    input   [15:0] RD_DATA, // read data from cpu to I2C

    // I2C 
    input           SCL,
    input           SDA_OUT,
    input           SDA_OE, //as requested by specification, it's an input, however it will not be used in logic.
    output  reg     SDA_IN
);



    reg _nxt_sda_o;
    reg [3:0] _count, _nxt_count;
    reg [7:0] _shift, _shifted;
    reg [15:0]_nxt_rd_data;
  
    reg [11:0] _state, _next_state;
    localparam  IDLE        = 12'b1,
                ADDR        = 12'b10,
                ACK         = 12'b100,
                WRITE_HIGH  = 12'b1000,
                WRITE_ACK   = 12'b10000,
                WRITE_LOW   = 12'b100000,
                READ_HIGH   = 12'b1000000,
                READ_ACK    = 12'b10000000,
                READ_LOW    = 12'b100000000,
                LAST_ACK    = 12'b1000000000;


reg scl_past, sda_past;

always @(posedge CLK or negedge RST) begin
    if (!RST) begin
        scl_past <= 1'b1;
    end else begin
        scl_past <= SCL;
        sda_past <= SDA_OUT;
    end
end
// Detects the exact CPU cycle SCL drops low
wire scl_falling_edge = (SCL == 0 && scl_past == 1);
// Detects the exact CPU cycle SCL rises high
wire scl_rising_edge  = (SCL == 1 && scl_past == 0);
wire scl_low  = (SCL == 0 && scl_past == 0);
wire scl_high = (SCL == 1 && scl_past == 1);
wire stop = (SDA_OUT == 1 && sda_past == 0 && scl_high);


    always @(*) begin
        _next_state = _state;
        _nxt_sda_o = SDA_IN;  
        _shifted = _shift;
        _nxt_rd_data = WR_DATA;
        _nxt_count = _count;
        case (_state)
            IDLE: begin
                _nxt_sda_o = 1;    
                if (SDA_OUT == 0 && scl_high) begin
                    _next_state = ADDR;
                    _nxt_count = 0;
                end
            end // ------------------------------- ADDR LOGIC -----------------------
            ADDR: begin
                if (scl_rising_edge)begin
                    _shifted = {_shift[6:0], SDA_OUT};
                    _nxt_count = _count + 1;
                end
                if (_count[3] == 1 && scl_falling_edge)begin
                    if (_shift[7:1] == I2C_ADDR) _next_state = ACK;
                    else _next_state = IDLE;
                end
            end
            ACK: begin
                _nxt_sda_o = 0; //ACK 
                if (scl_falling_edge) begin
                    // check RNW
                    if(_shift[0])begin
                        _next_state = READ_HIGH;
                        _shifted = RD_DATA[15:8];
                    end else _next_state = WRITE_HIGH;
                    _nxt_count = 3'b000;
                end
            end
            // ------------------------------------------------------------------WRITE LOGIC ---------------------------------------------------------------
            READ_HIGH: begin
                if (scl_low)begin
                    _nxt_sda_o = _shift[7];
                    _shifted = {_shift[6:0], 1'b1};
                    _nxt_count = _count + 1;
                end
                if (_count[3] && scl_falling_edge)begin
                    _next_state = READ_ACK;
                end
            end
            READ_ACK: begin
                if (scl_rising_edge && SDA_OUT == 1) begin //if NACK
                    _next_state = IDLE; 
                    _nxt_sda_o = 1;    
                end 
                if (scl_falling_edge) begin
                    _next_state = READ_LOW;
                    _nxt_count = 3'b000;
                    _shifted = RD_DATA[7:0];
                end
            end
            READ_LOW: begin
                if (scl_low)begin
                    _nxt_sda_o = _shift[7];
                    _shifted = {_shift[6:0], 1'b1};
                    _nxt_count = _count + 1;
                end
                if (_count[3]&& scl_falling_edge)begin
                    _next_state = IDLE;  // according to custom specification, only two bytes are sent and no more is required.
                end
            end
            // ------------------------------------------------------------------READ LOGIC ---------------------------------------------------------------
            WRITE_HIGH: begin
                _nxt_sda_o = 1;
                if (scl_rising_edge)begin
                    _shifted = {_shift[6:0], SDA_OUT};
                    _nxt_count = _count + 1;
                end
                if (_count[3] && scl_falling_edge)begin
                    _next_state = WRITE_ACK;
                end
            end
            WRITE_ACK: begin
                _nxt_sda_o = 0; //ACK 
                _nxt_rd_data = {_shift, 8'b0000000};
                if (scl_falling_edge) begin 
                    _next_state = WRITE_LOW;
                    _nxt_count = 3'b000;
                end
            end            
            WRITE_LOW: begin
                _nxt_sda_o = 1;
                if (scl_rising_edge)begin
                    _shifted = {_shift[6:0], SDA_OUT};
                    _nxt_count = _count + 1;
                end
                if (_count[3] && scl_falling_edge)begin
                    _next_state = LAST_ACK;
                end
            end
            LAST_ACK: begin // No ACK required according to custom specification
                _nxt_rd_data = {WR_DATA[15:8], _shift};
                _next_state = IDLE;
                _nxt_sda_o = 1;   
            end
        endcase
        if (stop) _next_state = IDLE;
    end


    always @(posedge CLK or negedge RST) begin
        if (!RST) begin
            //reset
            _state <= IDLE;
            SDA_IN <= 1'b1;
            _count <= 5'b0;
            _shift <= 8'b0;
        end else begin
            // not a reset
            _state <= _next_state;
            SDA_IN <= _nxt_sda_o;
            _count <= _nxt_count;
            _shift <= _shifted;
            WR_DATA <= _nxt_rd_data;
        end
    end





endmodule

sim/slave_testbench.v

//`include "build/i2c_receiver_synth.v" // Archivo generado por Yosys

`include "syn/cmos_cells.v"    // Celdas de la biblioteca para simulación


`include "src/i2c_receiver.v"
`include "sim/slave_tester.v"
`timescale 1ns / 1ps

module i2c_receiver_tb;

    // Clock is generated here, so it remains a reg
    reg         CLK;
    
    // Fixed: Signals driven by the tester outputs MUST be wires at the top level
    wire         RST;
    wire  [6:0]  I2C_ADDR;
    wire  [15:0] RD_DATA;
    wire         SCL;
    wire         SDA_OUT;
    wire         SDA_OE;

    // Outputs coming directly from the DUT
    wire [15:0] WR_DATA;
    wire        SDA_IN;

    // 1. Clock Generation (50MHz System Clock)
    initial CLK = 0;
    always begin
        #10 CLK = ~CLK; 
    end

    // 2. Instantiate the Design Under Test (DUT)
    i2c_receiver dut (
        .CLK(CLK),
        .RST(RST),
        .I2C_ADDR(I2C_ADDR),
        .WR_DATA(WR_DATA),
        .RD_DATA(RD_DATA),
        .SCL(SCL),
        .SDA_OUT(SDA_OUT),
        .SDA_OE(SDA_OE),
        .SDA_IN(SDA_IN)
    );

    // 3. Instantiate the Tester Module to drive stimulus
    tester test_driver (
        .CLK(CLK), // Input to tester
        .RST(RST),
        .I2C_ADDR(I2C_ADDR),
        .RD_DATA(RD_DATA),
        .SCL(SCL),
        .SDA_OUT(SDA_OUT),
        .SDA_OE(SDA_OE),
        .SDA_IN(SDA_IN),
        .WR_DATA(WR_DATA)
    );

    // 4. Waveform generation setup
    initial begin
        $dumpfile("i2c_simulation.vcd");
        $dumpvars(0, i2c_receiver_tb);
    end

endmodule

i2c_simulation.vcd
$date
	Sat Jun  6 08:21:16 2026
$end
$version
	Icarus Verilog
$end
$timescale
	1ps
$end
$scope module i2c_receiver_tb $end
$var wire 16 ! WR_DATA [15:0] $end
$var wire 1 " SDA_OUT $end
$var wire 1 # SDA_OE $end
$var wire 1 $ SDA_IN $end
$var wire 1 % SCL $end
$var wire 1 & RST $end
$var wire 16 ' RD_DATA [15:0] $end
$var wire 7 ( I2C_ADDR [6:0] $end
$var reg 1 ) CLK $end
$scope module dut $end
$var wire 1 ) CLK $end
$var wire 1 * scl_falling_edge $end
$var wire 1 + scl_high $end
$var wire 1 , scl_low $end
$var wire 1 - scl_rising_edge $end
$var wire 1 . stop $end
$var wire 1 " SDA_OUT $end
$var wire 1 # SDA_OE $end
$var wire 1 % SCL $end
$var wire 1 & RST $end
$var wire 16 / RD_DATA [15:0] $end
$var wire 7 0 I2C_ADDR [6:0] $end
$var parameter 12 1 ACK $end
$var parameter 12 2 ADDR $end
$var parameter 12 3 IDLE $end
$var parameter 12 4 LAST_ACK $end
$var parameter 12 5 READ_ACK $end
$var parameter 12 6 READ_HIGH $end
$var parameter 12 7 READ_LOW $end
$var parameter 12 8 WRITE_ACK $end
$var parameter 12 9 WRITE_HIGH $end
$var parameter 12 : WRITE_LOW $end
$var reg 1 $ SDA_IN $end
$var reg 16 ; WR_DATA [15:0] $end
$var reg 4 < _count [3:0] $end
$var reg 12 = _next_state [11:0] $end
$var reg 4 > _nxt_count [3:0] $end
$var reg 16 ? _nxt_rd_data [15:0] $end
$var reg 1 @ _nxt_sda_o $end
$var reg 8 A _shift [7:0] $end
$var reg 8 B _shifted [7:0] $end
$var reg 12 C _state [11:0] $end
$var reg 1 D scl_past $end
$var reg 1 E sda_past $end
$upscope $end
$scope module test_driver $end
$var wire 1 ) CLK $end
$var wire 1 $ SDA_IN $end
$var wire 16 F WR_DATA [15:0] $end
$var reg 7 G I2C_ADDR [6:0] $end
$var reg 16 H RD_DATA [15:0] $end
$var reg 1 & RST $end
$var reg 1 % SCL $end
$var reg 1 # SDA_OE $end
$var reg 1 " SDA_OUT $end
$scope begin rx_byte_loop $end
$var reg 8 I rx_byte [7:0] $end
$var integer 32 J i [31:0] $end
$upscope $end
$scope task send_i2c_bit $end
$var reg 1 K bit_val $end
$upscope $end
$upscope $end
$upscope $end
$enddefinitions $end
$comment Show the parameter values. $end
$dumpall
b100000 :
b1000 9
b10000 8
b100000000 7
b1000000 6
b10000000 5
b1000000000 4
b1 3
b10 2
b100 1
$end
#0
$dumpvars
xK
bx J
bx I
b1010101111001101 H
b1011010 G
bx F
xE
1D
b1 C
b0 B
b0 A
1@
bx ?
b0 >
b1 =
b0 <
bx ;
b1011010 0
b1010101111001101 /
x.
0-
0,
1+
0*
0)
b1011010 (
b1010101111001101 '
0&
1%
1$
1#
1"
bx !
$end
#10000
1)
#20000
0)
#30000
1)
#40000
0)
1&
#50000
0.
1E
1)
#60000
0)
#70000
1)
#80000
b10 =
0)
0"
#90000
b10 C
0E
1)
#100000
0+
1*
0)
0%
#110000
0*
1,
0D
1)
#120000
0)
1"
1K
#130000
1E
1)
#140000
0)
#150000
1)
#160000
b1 >
b1 B
0,
1-
0)
1%
#170000
0-
1+
b1 A
b1 <
1D
1)
#180000
0)
#190000
1)
#200000
0+
1*
0)
0"
0K
0%
#210000
0*
1,
0E
0D
1)
#220000
0)
#230000
1)
#240000
b10 >
b10 B
0,
1-
0)
1%
#250000
0-
1+
b10 A
b10 <
1D
1)
#260000
0)
#270000
1)
#280000
0+
1*
0)
1"
1K
0%
#290000
0*
1,
1E
0D
1)
#300000
0)
#310000
1)
#320000
b11 >
b101 B
0,
1-
0)
1%
#330000
0-
1+
b101 A
b11 <
1D
1)
#340000
0)
#350000
1)
#360000
0+
1*
0)
0%
#370000
0*
1,
0D
1)
#380000
0)
#390000
1)
#400000
b100 >
b1011 B
0,
1-
0)
1%
#410000
0-
1+
b1011 A
b100 <
1D
1)
#420000
0)
#430000
1)
#440000
0+
1*
0)
0"
0K
0%
#450000
0*
1,
0E
0D
1)
#460000
0)
#470000
1)
#480000
b101 >
b10110 B
0,
1-
0)
1%
#490000
0-
1+
b10110 A
b101 <
1D
1)
#500000
0)
#510000
1)
#520000
0+
1*
0)
1"
1K
0%
#530000
0*
1,
1E
0D
1)
#540000
0)
#550000
1)
#560000
b110 >
b101101 B
0,
1-
0)
1%
#570000
0-
1+
b101101 A
b110 <
1D
1)
#580000
0)
#590000
1)
#600000
0+
1*
0)
0"
0K
0%
#610000
0*
1,
0E
0D
1)
#620000
0)
#630000
1)
#640000
b111 >
b1011010 B
0,
1-
0)
1%
#650000
0-
1+
b1011010 A
b111 <
1D
1)
#660000
0)
#670000
1)
#680000
0+
1*
0)
0%
#690000
0*
1,
0D
1)
#700000
0)
#710000
1)
#720000
b1000 >
b10110100 B
0,
1-
0)
1%
#730000
0-
1+
b10110100 A
b1000 <
1D
1)
#740000
0)
#750000
1)
#760000
b100 =
0+
1*
0)
1"
0%
#770000
0@
0*
1,
b100 C
1E
0D
1)
#780000
0)
#790000
0$
1)
#800000
0,
1-
0)
1%
#810000
0-
1+
1D
1)
#820000
0)
#830000
1)
#840000
b0 >
b1000 =
0+
1*
0)
1K
0%
#850000
1@
0*
1,
b0 <
b1000 C
0D
1)
#860000
0)
#870000
1$
1)
#880000
b1 >
b1101001 B
0,
1-
0)
1%
#890000
0-
1+
b1101001 A
b1 <
1D
1)
#900000
0)
#910000
1)
#920000
0+
1*
0)
0"
0K
0%
#930000
0*
1,
0E
0D
1)
#940000
0)
#950000
1)
#960000
b10 >
b11010010 B
0,
1-
0)
1%
#970000
0-
1+
b11010010 A
b10 <
1D
1)
#980000
0)
#990000
1)
#1000000
0+
1*
0)
1"
1K
0%
#1010000
0*
1,
1E
0D
1)
#1020000
0)
#1030000
1)
#1040000
b11 >
b10100101 B
0,
1-
0)
1%
#1050000
0-
1+
b10100101 A
b11 <
1D
1)
#1060000
0)
#1070000
1)
#1080000
0+
1*
0)
0"
0K
0%
#1090000
0*
1,
0E
0D
1)
#1100000
0)
#1110000
1)
#1120000
b100 >
b1001010 B
0,
1-
0)
1%
#1130000
0-
1+
b1001010 A
b100 <
1D
1)
#1140000
0)
#1150000
1)
#1160000
0+
1*
0)
0%
#1170000
0*
1,
0D
1)
#1180000
0)
#1190000
1)
#1200000
b101 >
b10010100 B
0,
1-
0)
1%
#1210000
0-
1+
b10010100 A
b101 <
1D
1)
#1220000
0)
#1230000
1)
#1240000
0+
1*
0)
1"
1K
0%
#1250000
0*
1,
1E
0D
1)
#1260000
0)
#1270000
1)
#1280000
b110 >
b101001 B
0,
1-
0)
1%
#1290000
0-
1+
b101001 A
b110 <
1D
1)
#1300000
0)
#1310000
1)
#1320000
0+
1*
0)
0"
0K
0%
#1330000
0*
1,
0E
0D
1)
#1340000
0)
#1350000
1)
#1360000
b111 >
b1010010 B
0,
1-
0)
1%
#1370000
0-
1+
b1010010 A
b111 <
1D
1)
#1380000
0)
#1390000
1)
#1400000
0+
1*
0)
1"
1K
0%
#1410000
0*
1,
1E
0D
1)
#1420000
0)
#1430000
1)
#1440000
b1000 >
b10100101 B
0,
1-
0)
1%
#1450000
0-
1+
b10100101 A
b1000 <
1D
1)
#1460000
0)
#1470000
1)
#1480000
b10000 =
0+
1*
0)
0%
#1490000
b1010010100000000 ?
0@
0*
1,
b10000 C
0D
1)
#1500000
0)
#1510000
b1010010100000000 !
b1010010100000000 ;
b1010010100000000 F
0$
1)
#1520000
0,
1-
0)
1%
#1530000
0-
1+
1D
1)
#1540000
0)
#1550000
1)
#1560000
b0 >
b100000 =
0+
1*
0)
0%
#1570000
1@
0*
1,
b0 <
b100000 C
0D
1)
#1580000
0)
#1590000
1$
1)
#1600000
b1 >
b1001011 B
0,
1-
0)
1%
#1610000
0-
1+
b1001011 A
b1 <
1D
1)
#1620000
0)
#1630000
1)
#1640000
0+
1*
0)
0%
#1650000
0*
1,
0D
1)
#1660000
0)
#1670000
1)
#1680000
b10 >
b10010111 B
0,
1-
0)
1%
#1690000
0-
1+
b10010111 A
b10 <
1D
1)
#1700000
0)
#1710000
1)
#1720000
0+
1*
0)
0%
#1730000
0*
1,
0D
1)
#1740000
0)
#1750000
1)
#1760000
b11 >
b101111 B
0,
1-
0)
1%
#1770000
0-
1+
b101111 A
b11 <
1D
1)
#1780000
0)
#1790000
1)
#1800000
0+
1*
0)
0"
0K
0%
#1810000
0*
1,
0E
0D
1)
#1820000
0)
#1830000
1)
#1840000
b100 >
b1011110 B
0,
1-
0)
1%
#1850000
0-
1+
b1011110 A
b100 <
1D
1)
#1860000
0)
#1870000
1)
#1880000
0+
1*
0)
0%
#1890000
0*
1,
0D
1)
#1900000
0)
#1910000
1)
#1920000
b101 >
b10111100 B
0,
1-
0)
1%
#1930000
0-
1+
b10111100 A
b101 <
1D
1)
#1940000
0)
#1950000
1)
#1960000
0+
1*
0)
1"
1K
0%
#1970000
0*
1,
1E
0D
1)
#1980000
0)
#1990000
1)
#2000000
b110 >
b1111001 B
0,
1-
0)
1%
#2010000
0-
1+
b1111001 A
b110 <
1D
1)
#2020000
0)
#2030000
1)
#2040000
0+
1*
0)
0%
#2050000
0*
1,
0D
1)
#2060000
0)
#2070000
1)
#2080000
b111 >
b11110011 B
0,
1-
0)
1%
#2090000
0-
1+
b11110011 A
b111 <
1D
1)
#2100000
0)
#2110000
1)
#2120000
0+
1*
0)
0%
#2130000
0*
1,
0D
1)
#2140000
0)
#2150000
1)
#2160000
b1000 >
b11100111 B
0,
1-
0)
1%
#2170000
0-
1+
b11100111 A
b1000 <
1D
1)
#2180000
0)
#2190000
1)
#2200000
b1000000000 =
0+
1*
0)
0%
#2210000
b1 =
b1010010111100111 ?
0*
1,
b1000000000 C
0D
1)
#2220000
0)
#2230000
b1010010111100111 !
b1010010111100111 ;
b1010010111100111 F
b1 C
1)
#2240000
0,
1-
0)
1%
#2250000
0-
1+
1D
1)
#2260000
0)
#2270000
1)
#2280000
0+
1*
0)
0%
#2290000
0*
1,
0D
1)
#2300000
0)
#2310000
1)
#2320000
0)
0"
#2330000
0E
1)
#2340000
0,
1-
0)
1%
#2350000
b0 >
b10 =
0-
1+
1D
1)
#2360000
1.
b1000 >
b1 =
0)
1"
#2370000
0.
1E
1)
#2380000
0)
#2390000
1)
#2400000
0)
#2410000
1)
#2420000
0)
#2430000
1)
#2440000
0)
#2450000
1)
#2460000
0)
#2470000
1)
#2480000
0)
#2490000
1)
#2500000
0)
#2510000
1)
#2520000
b0 >
b10 =
0)
0"
#2530000
b0 <
b10 C
0E
1)
#2540000
0+
1*
0)
0%
#2550000
0*
1,
0D
1)
#2560000
0)
1"
#2570000
1E
1)
#2580000
0)
#2590000
1)
#2600000
b1 >
b11001111 B
0,
1-
0)
1%
#2610000
0-
1+
b11001111 A
b1 <
1D
1)
#2620000
0)
#2630000
1)
#2640000
0+
1*
0)
0"
0K
0%
#2650000
0*
1,
0E
0D
1)
#2660000
0)
#2670000
1)
#2680000
b10 >
b10011110 B
0,
1-
0)
1%
#2690000
0-
1+
b10011110 A
b10 <
1D
1)
#2700000
0)
#2710000
1)
#2720000
0+
1*
0)
1"
1K
0%
#2730000
0*
1,
1E
0D
1)
#2740000
0)
#2750000
1)
#2760000
b11 >
b111101 B
0,
1-
0)
1%
#2770000
0-
1+
b111101 A
b11 <
1D
1)
#2780000
0)
#2790000
1)
#2800000
0+
1*
0)
0%
#2810000
0*
1,
0D
1)
#2820000
0)
#2830000
1)
#2840000
b100 >
b1111011 B
0,
1-
0)
1%
#2850000
0-
1+
b1111011 A
b100 <
1D
1)
#2860000
0)
#2870000
1)
#2880000
0+
1*
0)
0"
0K
0%
#2890000
0*
1,
0E
0D
1)
#2900000
0)
#2910000
1)
#2920000
b101 >
b11110110 B
0,
1-
0)
1%
#2930000
0-
1+
b11110110 A
b101 <
1D
1)
#2940000
0)
#2950000
1)
#2960000
0+
1*
0)
1"
1K
0%
#2970000
0*
1,
1E
0D
1)
#2980000
0)
#2990000
1)
#3000000
b110 >
b11101101 B
0,
1-
0)
1%
#3010000
0-
1+
b11101101 A
b110 <
1D
1)
#3020000
0)
#3030000
1)
#3040000
0+
1*
0)
0"
0K
0%
#3050000
0*
1,
0E
0D
1)
#3060000
0)
#3070000
1)
#3080000
b111 >
b11011010 B
0,
1-
0)
1%
#3090000
0-
1+
b11011010 A
b111 <
1D
1)
#3100000
0)
#3110000
1)
#3120000
0+
1*
0)
1"
1K
0%
#3130000
0*
1,
1E
0D
1)
#3140000
0)
#3150000
1)
#3160000
b1000 >
b10110101 B
0,
1-
0)
1%
#3170000
0-
1+
b10110101 A
b1000 <
1D
1)
#3180000
0)
#3190000
1)
#3200000
b100 =
0+
1*
0)
0%
#3210000
0@
0*
1,
b100 C
0D
1)
#3220000
0)
#3230000
0$
1)
#3240000
0,
1-
0)
1%
#3250000
0-
1+
1D
1)
#3260000
0)
#3270000
1)
#3280000
b0 >
b10101011 B
b1000000 =
0+
1*
0)
b111 J
b0 I
0%
#3290000
b1 >
b1010111 B
1@
0*
1,
b10101011 A
b0 <
b1000000 C
0D
1)
#3300000
0)
#3310000
b10 >
b10101111 B
0@
b1010111 A
b1 <
1$
1)
#3320000
b1 >
b1010111 B
1@
0,
1-
0)
1%
#3330000
0-
1+
1D
1)
#3340000
0)
b10000000 I
#3350000
1)
#3360000
0+
1*
0)
b110 J
0%
#3370000
b10 >
b10101111 B
0@
0*
1,
0D
1)
#3380000
0)
#3390000
b11 >
b1011111 B
1@
b10101111 A
b10 <
0$
1)
#3400000
b10 >
b10101111 B
0@
0,
1-
0)
1%
#3410000
0-
1+
1D
1)
#3420000
0)
#3430000
1)
#3440000
0+
1*
0)
b101 J
0%
#3450000
b11 >
b1011111 B
1@
0*
1,
0D
1)
#3460000
0)
#3470000
b100 >
b10111111 B
0@
b1011111 A
b11 <
1$
1)
#3480000
b11 >
b1011111 B
1@
0,
1-
0)
1%
#3490000
0-
1+
1D
1)
#3500000
0)
b10100000 I
#3510000
1)
#3520000
0+
1*
0)
b100 J
0%
#3530000
b100 >
b10111111 B
0@
0*
1,
0D
1)
#3540000
0)
#3550000
b101 >
b1111111 B
1@
b10111111 A
b100 <
0$
1)
#3560000
b100 >
b10111111 B
0@
0,
1-
0)
1%
#3570000
0-
1+
1D
1)
#3580000
0)
#3590000
1)
#3600000
0+
1*
0)
b11 J
0%
#3610000
b101 >
b1111111 B
1@
0*
1,
0D
1)
#3620000
0)
#3630000
b110 >
b11111111 B
0@
b1111111 A
b101 <
1$
1)
#3640000
b101 >
b1111111 B
1@
0,
1-
0)
1%
#3650000
0-
1+
1D
1)
#3660000
0)
b10101000 I
#3670000
1)
#3680000
0+
1*
0)
b10 J
0%
#3690000
b110 >
b11111111 B
0@
0*
1,
0D
1)
#3700000
0)
#3710000
b111 >
1@
b11111111 A
b110 <
0$
1)
#3720000
b110 >
0@
0,
1-
0)
1%
#3730000
0-
1+
1D
1)
#3740000
0)
#3750000
1)
#3760000
0+
1*
0)
b1 J
0%
#3770000
b111 >
1@
0*
1,
0D
1)
#3780000
0)
#3790000
b1000 >
b111 <
1$
1)
#3800000
b111 >
0,
1-
0)
1%
#3810000
0-
1+
1D
1)
#3820000
0)
b10101010 I
#3830000
1)
#3840000
0+
1*
0)
b0 J
0%
#3850000
b1000 >
0*
1,
0D
1)
#3860000
0)
#3870000
b1001 >
b1000 <
1)
#3880000
b1000 >
0,
1-
0)
1%
#3890000
0-
1+
1D
1)
#3900000
0)
b10101011 I
#3910000
1)
#3920000
b10000000 =
0+
1*
0)
b11111111111111111111111111111111 J
0%
#3930000
0*
1,
b10000000 C
0D
1)
#3940000
0)
#3950000
1)
#3960000
0)
#3970000
1)
#3980000
b1 =
0,
1-
0)
1%
#3990000
0-
1+
1D
b1 C
1)
#4000000
0)
#4010000
1)
#4020000
0+
1*
0)
0%
#4030000
0*
1,
0D
1)
