src/i2c_receiver.v
module i2c_receiver (
    input          CLK,
    input          RST,      // RST=1 normal funstion, 0 restart

    // Interfaz con el CPU
    input   [6:0]  I2C_ADDR,
    output reg [15:0] WR_DATA, // write data to cpu from I2C
    input   [15:0] RD_DATA, // read data from cpu to I2C

    // I2C 
    input           SCL,
    input           SDA_OUT,
    input           SDA_OE, //as requested by specification, it's an input, however it will not be used in logic.
    output  reg     SDA_IN
);



    reg _nxt_sda_o;
    reg [3:0] _count, _nxt_count;
    reg [7:0] _shift, _shifted;
    reg [15:0]_nxt_rd_data;
  
    reg [11:0] _state, _next_state;
    localparam  IDLE        = 12'b1,
                ADDR        = 12'b10,
                ACK         = 12'b100,
                WRITE_HIGH  = 12'b1000,
                WRITE_ACK   = 12'b10000,
                WRITE_LOW   = 12'b100000,
                READ_HIGH   = 12'b1000000,
                READ_ACK    = 12'b10000000,
                READ_LOW    = 12'b100000000,
                LAST_ACK    = 12'b1000000000;


reg scl_past, sda_past;

always @(posedge CLK or negedge RST) begin
    if (!RST) begin
        scl_past <= 1'b1;
    end else begin
        scl_past <= SCL;
        sda_past <= SDA_OUT;
    end
end
// Detects the exact CPU cycle SCL drops low
wire scl_falling_edge = (SCL == 0 && scl_past == 1);
// Detects the exact CPU cycle SCL rises high
wire scl_rising_edge  = (SCL == 1 && scl_past == 0);
wire scl_low  = (SCL == 0 && scl_past == 0);
wire scl_high = (SCL == 1 && scl_past == 1);
wire stop = (SDA_OUT == 1 && sda_past == 0 && scl_high);


    always @(*) begin
        _next_state = _state;
        _nxt_sda_o = SDA_IN;  
        _shifted = _shift;
        _nxt_rd_data = WR_DATA;
        _nxt_count = _count;
        case (_state)
            IDLE: begin
                _nxt_sda_o = 1;    
                if (SDA_OUT == 0 && scl_high) begin
                    _next_state = ADDR;
                    _nxt_count = 0;
                end
            end // ------------------------------- ADDR LOGIC -----------------------
            ADDR: begin
                if (scl_rising_edge)begin
                    _shifted = {_shift[6:0], SDA_OUT};
                    _nxt_count = _count + 1;
                end
                if (_count[3] == 1 && scl_falling_edge)begin
                    if (_shift[7:1] == I2C_ADDR) _next_state = ACK;
                    else _next_state = IDLE;
                end
            end
            ACK: begin
                _nxt_sda_o = 0; //ACK 
                if (scl_falling_edge) begin
                    // check RNW
                    if(_shift[0])begin
                        _next_state = READ_HIGH;
                        _shifted = RD_DATA[15:8];
                    end else _next_state = WRITE_HIGH;
                    _nxt_count = 3'b000;
                end
            end
            // ------------------------------------------------------------------WRITE LOGIC ---------------------------------------------------------------
            READ_HIGH: begin
                if (scl_low)begin
                    _nxt_sda_o = _shift[7];
                    _shifted = {_shift[6:0], 1'b1};
                    _nxt_count = _count + 1;
                end
                if (_count == 3'b111 && scl_falling_edge)begin
                    _next_state = READ_ACK;
                end
            end
            READ_ACK: begin
                if (scl_rising_edge && SDA_OUT == 1) begin //if NACK
                    _next_state = IDLE; 
                    _nxt_sda_o = 1;    
                end 
                if (scl_falling_edge) begin
                    _next_state = READ_LOW;
                    _nxt_count = 3'b000;
                    _shifted = RD_DATA[7:0];
                end
            end
            READ_LOW: begin
                if (scl_low)begin
                    _nxt_sda_o = _shift[7];
                    _shifted = {_shift[6:0], 1'b1};
                    _nxt_count = _count + 1;
                end
                if (_count == 3'b111 && scl_falling_edge)begin
                    _next_state = IDLE;  // according to custom specification, only two bytes are sent and no more is required.
                end
            end
            // ------------------------------------------------------------------READ LOGIC ---------------------------------------------------------------
            WRITE_HIGH: begin
                _nxt_sda_o = 1;
                if (scl_rising_edge)begin
                    _shifted = {_shift[6:0], SDA_OUT};
                    _nxt_count = _count + 1;
                end
                if (_count[3] && scl_falling_edge)begin
                    _next_state = WRITE_ACK;
                end
            end
            WRITE_ACK: begin
                _nxt_sda_o = 0; //ACK 
                _nxt_rd_data = {_shift, 8'b0000000};
                if (scl_falling_edge) begin 
                    _next_state = WRITE_LOW;
                    _nxt_count = 3'b000;
                end
            end            
            WRITE_LOW: begin
                _nxt_sda_o = 1;
                if (scl_rising_edge)begin
                    _shifted = {_shift[6:0], SDA_OUT};
                    _nxt_count = _count + 1;
                end
                if (_count[3] && scl_falling_edge)begin
                    _next_state = LAST_ACK;
                end
            end
            LAST_ACK: begin // No ACK required according to custom specification
                _nxt_rd_data = {WR_DATA[15:8], _shift};
                _next_state = IDLE;
                _nxt_sda_o = 1;   
            end
        endcase
        if (stop) _next_state = IDLE;
    end


    always @(posedge CLK or negedge RST) begin
        if (!RST) begin
            //reset
            _state <= IDLE;
            SDA_IN <= 1'b1;
            _count <= 5'b0;
            _shift <= 8'b0;
        end else begin
            // not a reset
            _state <= _next_state;
            SDA_IN <= _nxt_sda_o;
            _count <= _nxt_count;
            _shift <= _shifted;
            WR_DATA <= _nxt_rd_data;
        end
    end





endmodule

src/i2c_generator.v
module i2c_generator (
    // Reloj y Reinicio
    input          CLK,
    input          RST,      // RST=1 para funcionamiento normal, 0 para reinicio

    // Interfaz con el CPU
    input          RNW,
    input   [6:0]  I2C_ADDR,
    input   [15:0] WR_DATA, //write data from cpu to I2C
    output reg [15:0] RD_DATA, //read data from I2C to cpu
    input          START_STB,

    // Interfaz Física I2C / Probador
    output reg        SCL,
    output reg        SDA_OUT,
    output reg        SDA_OE,
    input         SDA_IN
);


    reg _nxt_sda_o;
    reg [4:0] _stage_count, _nxt_stage_count;
    reg [7:0] _shift, _shifted;
    reg [15:0]_nxt_rd_data;
  
    reg [:0] _state, _next_state;
    localparam  IDLE        = 12'b1
                START       = 12'b10
                ADDR        = 12'b100
                ACK         = 12'b1000
                WRITE_HIGH  = 12'b10000
                WRITE_ACK   = 12'b100000
                WRITE_LOW   = 12'b1000000
                WAIT_ACK    = 12'b10000000
                READ_HIGH   = 12'b100000000
                READ_ACK    = 12'b1000000000
                READ_LOW    = 12'b10000000000
                LAST_ACK    = 12'b100000000000

    always @(*) begin
        SDA_OE = 1;
        _next_state = _state;
        _nxt_sda_o = SDA_OUT;  
        _shifted = _shift;
        _nxt_rd_data = RD_DATA;
        case (_state)
            IDLE: begin
                _nxt_stage_count = 5'b11111;
                _nxt_sda_o = 1;    
                if (START_STB) begin
                    _next_state = START;
                    _nxt_sda_o = 0;
                end
            end
            START: begin
                _nxt_stage_count = _stage_count +1;
                _nxt_sda_o = 0;  
                _next_state = ADDR;
                _shifted = {I2C_ADDR, RNW};
            end
            ADDR: begin
                _nxt_stage_count = _stage_count +1;
                if (_stage_count[1:0] == 2'b00)begin
                    _nxt_sda_o = _shift[7];
                    _shifted = {shift_reg[6:0], 1'b1};
                end
                if (_stage_count[4:2] == 3'b111)begin
                    _next_state = ACK;
                end
            end
            ACK: begin
                _nxt_stage_count = _stage_count +1;
                if (_stage_count != 0) begin
                    SDA_OE = 0;
                    if (_stage_count[1:0] == 2'b10 && SDA_IN == 0) begin //if NACK
                        _next_state = IDLE; 
                    end 
                    if (_stage_count[1:0] == 2'b11) begin
                        _next_state = (RNW)? READ_HIGH : WRITE_HIGH;
                        _nxt_stage_count = 5'b00000;
                        _shifted = WR_DATA[15:8];
                    end
                end
            end
            // ------------------------------------------------------------------WRITE LOGIC ---------------------------------------------------------------
            WRITE_HIGH: begin
                _nxt_stage_count = _stage_count +1;
                if (_stage_count[1:0] == 2'b00)begin
                    _nxt_sda_o = _shift[7];
                    _shifted = {shift_reg[6:0], 1'b1};
                end
                if (_stage_count[4:2] == 3'b111)begin
                    _next_state = WRITE_ACK;
                end
            end
            WRITE_ACK: begin
                _nxt_stage_count = _stage_count +1;
                if (_stage_count != 0) begin
                    SDA_OE = 0;
                    if (_stage_count[1:0] == 2'b10 && SDA_IN == 1) begin //if NACK
                        _next_state = IDLE; 
                    end 
                    if (_stage_count[1:0] == 2'b11) begin
                        _next_state = WRITE_LOW;
                        _nxt_stage_count = 5'b00000;
                        _shifted = WR_DATA[7:0];
                    end
                end
            end
            WRITE_LOW: begin
                _nxt_stage_count = _stage_count +1;
                if (_stage_count[1:0] == 2'b00)begin
                    _nxt_sda_o = _shift[7];
                    _shifted = {shift_reg[6:0], 1'b1};
                end
                if (_stage_count[4:2] == 3'b111)begin
                    _next_state = WAIT_ACK;
                end
            end
            WAIT_ACK: begin
                _nxt_stage_count = _stage_count +1;
                if (_stage_count != 0) begin
                    SDA_OE = 0;
                    if (_stage_count[1:0] == 2'b10) begin 
                        _next_state = IDLE;  //STOP
                    end 
                end
            end
            // ------------------------------------------------------------------READ LOGIC ---------------------------------------------------------------
            READ_HIGH: begin
                _nxt_stage_count = _stage_count +1;
                if (_stage_count != 0) SDA_OE = 0;
                if (_stage_count[1:0] == 2'b10)begin
                    _shifted = {shift_reg[6:0], SDA_IN};
                end
                if (_stage_count[4:2] == 3'b111)begin
                    _next_state = READ_ACK;
                end
            end
            READ_ACK: begin
                _nxt_sda_o = 0; //ACK 
                _nxt_rd_data = {_shift, 8'b0000000};
                _nxt_stage_count = _stage_count +1;
                if (_stage_count == 0) SDA_OE = 0;
                else begin
                    if (_stage_count[2:0] == 2'b11) begin
                        _next_state = READ_LOW;
                        _nxt_stage_count = 5'b00000;
                    end
                end
            end            
            READ_LOW: begin
                if (_stage_count != 0) SDA_OE = 0;
                _nxt_stage_count = _stage_count +1;
                SDA_OE = 0;
                if (_stage_count[1:0] == 2'b10)begin
                    _shifted = {shift_reg[6:0], SDA_IN};
                end
                if (_stage_count[4:2] == 3'b111)begin
                    _next_state = LAST_ACK;
                end
            end
            LAST_ACK: begin
                _nxt_sda_o = 0; //ACK 
                _nxt_rd_data = {RD_DATA[15:8], _shift};
                _nxt_stage_count = _stage_count +1;
                if (_stage_count == 0) SDA_OE = 0;
                else begin
                    if (_stage_count[2:0] == 3'b110) begin
                        _next_state = IDLE;
                    end
                end
            end
        endcase
    end


    always @(posedge CLK or negedge RST) begin
        if (!RST) begin
            //reset
            _state <= IDLE;
            SDA_OUT <= 1'b1;
            SCL <= 1'b1;
            SDA_OE <= 1'b0;
            _stage_count <= 5'b0;
            _shift <= 8'b0;
        end else begin
            // not a reset
            _state <= _next_state;
            SDA_OUT <= _nxt_sda_o;
            SCL <= _nxt_stage_count[1];
            _stage_count <= _nxt_stage_count;
            _shift <= _shifted;
            RD_DATA <= _nxt_rd_data;
        end
    end

endmodule

sim/tester.v
`timescale 1ns / 1ps

module tester (
    // Outputs to the System/DUT
    output reg        CLK,
    output reg        MRST,
    output reg        SRST,
    output reg        RNW,
    output reg [6:0]  I2C_ADDR,
    output reg        START_STB,
    output reg [15:0] MWR_DATA,
    output reg [15:0] SRD_DATA, // Data slave sends when read

    // Inputs from the System/DUT
    input      [15:0] MRD_DATA, // Data master captured from read
    input      [15:0] SWR_DATA  // Data slave captured from write
);

    // --- 1. Clock Generation ---
    // 50MHz Clock (20ns period -> toggles every 10ns)
    always begin
        #10 CLK = ~CLK;
    end

    // --- 2. Test Stimulus Logic ---
    initial begin
        // Initialize all output registers
        CLK        = 0;
        MRST       = 1;
        SRST       = 1;
        RNW        = 0;
        I2C_ADDR   = 7'h00;
        START_STB  = 0;
        MWR_DATA   = 16'h0000;
        SRD_DATA   = 16'hABCD; // Pre-load slave with data to be read

        // Hold reset for 5 clock cycles
        repeat (5) @(posedge CLK);
        #1; // Small delay to avoid racing with the clock edge
        MRST       = 0;
        SRST       = 0;
        
        repeat (2) @(posedge CLK);

        // ==========================================
        // TRANSACTION 1: Master Writes to Slave
        // ==========================================
        $display("[TESTER] Starting I2C Write Transaction...");
        I2C_ADDR   = 7'h5A;          // Target Slave Address
        MWR_DATA   = 16'hCAFE;        // Data payload to write
        RNW        = 0;               // 0 = Write
        START_STB  = 1;               // Assert start strobe
        
        repeat (2) @(posedge CLK);
        #1;
        START_STB  = 0;               // De-assert strobe after 1 clock cycle

        // Wait for the transmission to finish.
        // (Adjust this delay based on your actual I2C clock speed divider)
        // For standard 100kHz I2C, a 2-byte frame takes roughly 200,000ns.
        #2500; 

        // Verify if slave captured the data correctly
        if (SWR_DATA === 16'hCAFE) begin
            $display("[TESTER] SUCCESS: Slave successfully received 16'hCAFE");
        end else begin
            $display("[TESTER] ERROR: Slave data mismatch. Expected 16'hCAFE, Got 16'h%h", SWR_DATA);
        end

        repeat (10) @(posedge CLK);

        // ==========================================
        // TRANSACTION 2: Master Reads from Slave
        // ==========================================
        $display("[TESTER] Starting I2C Read Transaction...");
        I2C_ADDR   = 7'h5A;          // Target Slave Address
        RNW        = 1;               // 1 = Read
        START_STB  = 1;
        
        @(posedge CLK);
        #1;
        START_STB  = 0;

        #2500; // Wait for read sequence to completely finish

        // Verify if master captured the data sent by the slave
        if (MRD_DATA === 16'hABCD) begin
            $display("[TESTER] SUCCESS: Master successfully read 16'hABCD");
        end else begin
            $display("[TESTER] ERROR: Master data mismatch. Expected 16'hABCD, Got 16'h%h", MRD_DATA);
        end

        // End Simulation
        repeat (20) @(posedge CLK);
        $display("[TESTER] Simulation finished cleanly.");
        $finish;
    end

endmodule

sim/testbench_nosynth.v
//`include "build/i2c_generator_synth.v" // Archivo generado por Yosys
//`include "build/i2c_receiver_synth.v" // Archivo generado por Yosys

`include "syn/cmos_cells.v"    // Celdas de la biblioteca para simulación



`include "src/i2c_receiver.v"
`include "src/i2c_generator.v"
`include "sim/tester.v"


`timescale 1ns / 1ps

module tb_i2c_generator();

    // Interconnect wires (CPU Side)
    wire        clk;
    wire        rst_master;
    wire        rnw;
    wire [6:0]  i2c_addr;
    wire [15:0] wr_data;
    wire        start_stb;
    wire [15:0] rd_data;

    // Interconnect wires (I2C Physical Side)
    wire        scl;
    wire        sda_out;
    wire        sda_oe;
    wire        sda_in;
    

    // Instantiate the Tester Module
    tester u_tester (
        .CLK(clk),
        .MRST(rst_master),
        .SRST(rst_slave),
        .RNW(rnw),
        .I2C_ADDR(i2c_addr),
        .START_STB(start_stb),
        .MWR_DATA(wr_data),
        .MRD_DATA(rd_data),
        .SWR_DATA(wr_data_slave),
        .SRD_DATA(rd_data_slave)
    );

    // Instantiate the Design Under Test (DUT)
    i2c_generator dut_master (
        .CLK(clk),
        .RST(~rst_master),
        .RNW(rnw),
        .I2C_ADDR(i2c_addr),
        .WR_DATA(wr_data),
        .RD_DATA(rd_data),
        .START_STB(start_stb),
        .SCL(scl),
        .SDA_OUT(sda_out),
        .SDA_OE(sda_oe),
        .SDA_IN(sda_in) // Inout resolution handling inside the system
    );
    i2c_receiver dut_slave (
        .CLK(clk),
        .RST(~rst_slave),
        .I2C_ADDR(i2c_addr),
        .WR_DATA(wr_data_slave),
        .RD_DATA(rd_data_slave),
        .SCL(scl),
        .SDA_OUT(sda_out),
        .SDA_OE(sda_oe),
        .SDA_IN(sda_in)
    );

    // Waveform setup for visualization
    initial begin
        $dumpfile("i2c_simulation.vcd");
        $dumpvars(0, tb_i2c_generator);
    end

endmodule

i2c_simulation.vcd
$date
	Sat Jun  6 09:07:27 2026
$end
$version
	Icarus Verilog
$end
$timescale
	1ps
$end
$scope module tb_i2c_generator $end
$var wire 1 ! wr_data_slave $end
$var wire 16 " wr_data [15:0] $end
$var wire 1 # start_stb $end
$var wire 1 $ sda_out $end
$var wire 1 % sda_oe $end
$var wire 1 & sda_in $end
$var wire 1 ' scl $end
$var wire 1 ( rst_slave $end
$var wire 1 ) rst_master $end
$var wire 1 * rnw $end
$var wire 1 + rd_data_slave $end
$var wire 16 , rd_data [15:0] $end
$var wire 7 - i2c_addr [6:0] $end
$var wire 1 . clk $end
$scope module dut_master $end
$var wire 1 / RST $end
$var wire 16 0 WR_DATA [15:0] $end
$var wire 1 # START_STB $end
$var wire 1 & SDA_IN $end
$var wire 1 * RNW $end
$var wire 7 1 I2C_ADDR [6:0] $end
$var wire 1 . CLK $end
$var parameter 12 2 ACK $end
$var parameter 12 3 ADDR $end
$var parameter 12 4 IDLE $end
$var parameter 12 5 LAST_ACK $end
$var parameter 12 6 READ_ACK $end
$var parameter 12 7 READ_HIGH $end
$var parameter 12 8 READ_LOW $end
$var parameter 12 9 START $end
$var parameter 12 : WAIT_ACK $end
$var parameter 12 ; WRITE_ACK $end
$var parameter 12 < WRITE_HIGH $end
$var parameter 12 = WRITE_LOW $end
$var reg 16 > RD_DATA [15:0] $end
$var reg 1 ' SCL $end
$var reg 1 % SDA_OE $end
$var reg 1 $ SDA_OUT $end
$var reg 12 ? _next_state [11:0] $end
$var reg 16 @ _nxt_rd_data [15:0] $end
$var reg 1 A _nxt_sda_o $end
$var reg 5 B _nxt_stage_count [4:0] $end
$var reg 8 C _shift [7:0] $end
$var reg 8 D _shifted [7:0] $end
$var reg 5 E _stage_count [4:0] $end
$var reg 12 F _state [11:0] $end
$upscope $end
$scope module dut_slave $end
$var wire 16 G RD_DATA [15:0] $end
$var wire 1 H RST $end
$var wire 1 ' SCL $end
$var wire 1 % SDA_OE $end
$var wire 1 $ SDA_OUT $end
$var wire 1 I scl_falling_edge $end
$var wire 1 J scl_high $end
$var wire 1 K scl_low $end
$var wire 1 L scl_rising_edge $end
$var wire 1 M stop $end
$var wire 7 N I2C_ADDR [6:0] $end
$var wire 1 . CLK $end
$var parameter 12 O ACK $end
$var parameter 12 P ADDR $end
$var parameter 12 Q IDLE $end
$var parameter 12 R LAST_ACK $end
$var parameter 12 S READ_ACK $end
$var parameter 12 T READ_HIGH $end
$var parameter 12 U READ_LOW $end
$var parameter 12 V WRITE_ACK $end
$var parameter 12 W WRITE_HIGH $end
$var parameter 12 X WRITE_LOW $end
$var reg 1 & SDA_IN $end
$var reg 16 Y WR_DATA [15:0] $end
$var reg 4 Z _count [3:0] $end
$var reg 12 [ _next_state [11:0] $end
$var reg 4 \ _nxt_count [3:0] $end
$var reg 16 ] _nxt_rd_data [15:0] $end
$var reg 1 ^ _nxt_sda_o $end
$var reg 8 _ _shift [7:0] $end
$var reg 8 ` _shifted [7:0] $end
$var reg 12 a _state [11:0] $end
$var reg 1 b scl_past $end
$var reg 1 c sda_past $end
$upscope $end
$scope module u_tester $end
$var wire 16 d MRD_DATA [15:0] $end
$var wire 16 e SWR_DATA [15:0] $end
$var reg 1 . CLK $end
$var reg 7 f I2C_ADDR [6:0] $end
$var reg 1 ) MRST $end
$var reg 16 g MWR_DATA [15:0] $end
$var reg 1 * RNW $end
$var reg 16 h SRD_DATA [15:0] $end
$var reg 1 ( SRST $end
$var reg 1 # START_STB $end
$upscope $end
$upscope $end
$enddefinitions $end
$comment Show the parameter values. $end
$dumpall
b100000 X
b1000 W
b10000 V
b100000000 U
b1000000 T
b10000000 S
b1000000000 R
b1 Q
b10 P
b100 O
b1000000 =
b10000 <
b100000 ;
b10000000 :
b10 9
b10000000000 8
b100000000 7
b1000000000 6
b100000000000 5
b1 4
b100 3
b1000 2
$end
#0
$dumpvars
b1010101111001101 h
b0 g
b0 f
b0x e
bx d
xc
1b
b1 a
b0 `
b0 _
1^
bx ]
b0 \
b1 [
b0 Z
bx Y
b0 N
xM
0L
0K
1J
0I
0H
b1 G
b1 F
b0 E
b0 D
b0 C
b11111 B
1A
bx @
b1 ?
bx >
b0 1
b0 0
0/
0.
b0 -
bx ,
1+
0*
1)
1(
1'
1&
1%
1$
0#
b0 "
x!
$end
#10000
0%
1.
#20000
0.
#30000
1.
#40000
0.
#50000
1.
#60000
0.
#70000
1.
#80000
0.
#90000
1.
#91000
1H
1/
0(
0)
#100000
0.
#110000
0M
1%
b11111 E
1c
1.
#120000
0.
#130000
0A
b10 ?
1#
b1100101011111110 "
b1100101011111110 0
b1100101011111110 g
b1011010 -
b1011010 1
b1011010 N
b1011010 f
1.
#140000
0.
#150000
b10 [
b10110100 D
b100 ?
b0 B
0$
b10 F
1.
#160000
0.
#170000
1I
0J
b1101001 D
1A
b1 B
b10110100 C
b0 E
0'
b100 F
b10 a
0c
1.
#171000
b1101001 D
1A
0#
#180000
0.
#190000
b10 B
0I
1K
b1101001 C
b1 E
1$
0b
1.
#200000
0.
#210000
b1 \
b1 `
b11 B
1L
0K
b10 E
1'
1c
1.
#220000
0.
#230000
b100 B
0L
1J
b1 \
b1 `
b11 E
1b
b1 _
b1 Z
1.
#240000
0.
#250000
b11010011 D
0A
b101 B
1I
0J
b100 E
0'
1.
#260000
0.
#270000
b110 B
0I
1K
b11010011 C
b101 E
0$
0b
1.
#280000
0.
#290000
b10 \
b10 `
b111 B
1L
0K
b110 E
1'
0c
1.
#300000
0.
#310000
b1000 B
0L
1J
b10 \
b10 `
b111 E
1b
b10 _
b10 Z
1.
#320000
0.
#330000
b10100111 D
1A
b1001 B
1I
0J
b1000 E
0'
1.
#340000
0.
#350000
b1010 B
0I
1K
b10100111 C
b1001 E
1$
0b
1.
#360000
0.
#370000
b11 \
b101 `
b1011 B
1L
0K
b1010 E
1'
1c
1.
#380000
0.
#390000
b1100 B
0L
1J
b11 \
b101 `
b1011 E
1b
b101 _
b11 Z
1.
#400000
0.
#410000
b1001111 D
b1101 B
1I
0J
b1100 E
0'
1.
#420000
0.
#430000
b1110 B
0I
1K
b1001111 C
b1101 E
0b
1.
#440000
0.
#450000
b100 \
b1011 `
b1111 B
1L
0K
b1110 E
1'
1.
#460000
0.
#470000
b10000 B
0L
1J
b100 \
b1011 `
b1111 E
1b
b1011 _
b100 Z
1.
#480000
0.
#490000
b10011111 D
0A
b10001 B
1I
0J
b10000 E
0'
1.
#500000
0.
#510000
b10010 B
0I
1K
b10011111 C
b10001 E
0$
0b
1.
#520000
0.
#530000
b101 \
b10110 `
b10011 B
1L
0K
b10010 E
1'
0c
1.
#540000
0.
#550000
b10100 B
0L
1J
b101 \
b10110 `
b10011 E
1b
b10110 _
b101 Z
1.
#560000
0.
#570000
b111111 D
1A
b10101 B
1I
0J
b10100 E
0'
1.
#580000
0.
#590000
b10110 B
0I
1K
b111111 C
b10101 E
1$
0b
1.
#600000
0.
#610000
b110 \
b101101 `
b10111 B
1L
0K
b10110 E
1'
1c
1.
#620000
0.
#630000
b11000 B
0L
1J
b110 \
b101101 `
b10111 E
1b
b101101 _
b110 Z
1.
#640000
0.
#650000
b1111111 D
0A
b11001 B
1I
0J
b11000 E
0'
1.
#660000
0.
#670000
b11010 B
0I
1K
b1111111 C
b11001 E
0$
0b
1.
#680000
0.
#690000
b111 \
b1011010 `
b11011 B
1L
0K
b11010 E
1'
0c
1.
#700000
0.
#710000
b11100 B
0L
1J
b111 \
b1011010 `
b11011 E
1b
b1011010 _
b111 Z
1.
#720000
0.
#730000
b11111111 D
b11101 B
1I
0J
b11100 E
0'
1.
#740000
0.
#750000
b11110 B
0I
1K
b11111111 C
b11101 E
0b
1.
#760000
0.
#770000
b1000 \
b10110100 `
b11111 B
1L
0K
b11110 E
1'
1.
#780000
0.
#790000
b1000 ?
b0 B
0L
1J
b1000 \
b10110100 `
b11111 E
1b
b10110100 _
b1000 Z
1.
#800000
0.
#810000
b100 [
1I
0J
b1 B
b0 E
0'
b1000 F
1.
#820000
0.
#830000
0%
b10 B
0I
1K
b1000 \
b100 [
0^
b1 E
0b
b100 a
1.
#840000
0.
#850000
1L
0K
b11 B
0%
b10 E
1'
0&
1.
#860000
0.
#870000
b11001010 D
b10000 ?
b0 B
0%
0L
1J
b11 E
1b
1.
#880000
0.
#890000
b0 \
b1000 [
1I
0J
b10010101 D
1A
b1 B
0%
b11001010 C
b0 E
0'
b10000 F
1.
#900000
0.
#910000
b10 B
1%
0I
1K
1^
b10010101 C
b1 E
1$
0b
b0 Z
b1000 a
1.
#920000
0.
#930000
b1 \
b1101001 `
1L
0K
b11 B
b10 E
1'
1&
1c
1.
#940000
0.
#950000
b100 B
0L
1J
b1 \
b1101001 `
b11 E
1b
b1101001 _
b1 Z
1.
#960000
0.
#970000
b101011 D
b101 B
1I
0J
b100 E
0'
1.
#980000
0.
#990000
b110 B
0I
1K
b101011 C
b101 E
0b
1.
#1000000
0.
#1010000
b10 \
b11010011 `
b111 B
1L
0K
b110 E
1'
1.
#1020000
0.
#1030000
b1000 B
0L
1J
b10 \
b11010011 `
b111 E
1b
b11010011 _
b10 Z
1.
#1040000
0.
#1050000
b1010111 D
0A
b1001 B
1I
0J
b1000 E
0'
1.
#1060000
0.
#1070000
b1010 B
0I
1K
b1010111 C
b1001 E
0$
0b
1.
#1080000
0.
#1090000
b11 \
b10100110 `
b1011 B
1L
0K
b1010 E
1'
0c
1.
#1100000
0.
#1110000
b1100 B
0L
1J
b11 \
b10100110 `
b1011 E
1b
b10100110 _
b11 Z
1.
#1120000
0.
#1130000
b10101111 D
b1101 B
1I
0J
b1100 E
0'
1.
#1140000
0.
#1150000
b1110 B
0I
1K
b10101111 C
b1101 E
0b
1.
#1160000
0.
#1170000
b100 \
b1001100 `
b1111 B
1L
0K
b1110 E
1'
1.
#1180000
0.
#1190000
b10000 B
0L
1J
b100 \
b1001100 `
b1111 E
1b
b1001100 _
b100 Z
1.
#1200000
0.
#1210000
b1011111 D
1A
b10001 B
1I
0J
b10000 E
0'
1.
#1220000
0.
#1230000
b10010 B
0I
1K
b1011111 C
b10001 E
1$
0b
1.
#1240000
0.
#1250000
b101 \
b10011001 `
b10011 B
1L
0K
b10010 E
1'
1c
1.
#1260000
0.
#1270000
b10100 B
0L
1J
b101 \
b10011001 `
b10011 E
1b
b10011001 _
b101 Z
1.
#1280000
0.
#1290000
b10111111 D
0A
b10101 B
1I
0J
b10100 E
0'
1.
#1300000
0.
#1310000
b10110 B
0I
1K
b10111111 C
b10101 E
0$
0b
1.
#1320000
0.
#1330000
b110 \
b110010 `
b10111 B
1L
0K
b10110 E
1'
0c
1.
#1340000
0.
#1350000
b11000 B
0L
1J
b110 \
b110010 `
b10111 E
1b
b110010 _
b110 Z
1.
#1360000
0.
#1370000
b1111111 D
1A
b11001 B
1I
0J
b11000 E
0'
1.
#1380000
0.
#1390000
b11010 B
0I
1K
b1111111 C
b11001 E
1$
0b
1.
#1400000
0.
#1410000
b111 \
b1100101 `
b11011 B
1L
0K
b11010 E
1'
1c
1.
#1420000
0.
#1430000
b11100 B
0L
1J
b111 \
b1100101 `
b11011 E
1b
b1100101 _
b111 Z
1.
#1440000
0.
#1450000
b11111111 D
0A
b11101 B
1I
0J
b11100 E
0'
1.
#1460000
0.
#1470000
b11110 B
0I
1K
b11111111 C
b11101 E
0$
0b
1.
#1480000
0.
#1490000
b1000 \
b11001010 `
b11111 B
1L
0K
b11110 E
1'
0c
1.
#1500000
0.
#1510000
b100000 ?
b0 B
0L
1J
b1000 \
b11001010 `
b11111 E
1b
b11001010 _
b1000 Z
1.
#1520000
0.
#1530000
b10000 [
1I
0J
b1 B
b0 E
0'
b100000 F
1.
#1540000
0.
#1550000
0%
b10 B
0I
1K
b1000 \
b10000 [
b1100101000000000 ]
0^
b1 E
0b
b10000 a
1.
#1560000
0.
#1570000
1L
0K
b0 e
0!
b11 B
0%
b10 E
1'
b1100101000000000 Y
0&
1.
#1580000
0.
#1590000
b11111110 D
b1000000 ?
b0 B
0%
0L
1J
b11 E
1b
1.
#1600000
0.
#1610000
b0 \
b100000 [
1I
0J
b11111101 D
1A
b1 B
0%
b11111110 C
b0 E
0'
b1000000 F
1.
#1620000
0.
#1630000
b10 B
1%
0I
1K
1^
b11111101 C
b1 E
1$
0b
b0 Z
b100000 a
1.
#1640000
0.
#1650000
b1 \
b10010101 `
1L
0K
b11 B
b10 E
1'
1&
1c
1.
#1660000
0.
#1670000
b100 B
0L
1J
b1 \
b10010101 `
b11 E
1b
b10010101 _
b1 Z
1.
#1680000
0.
#1690000
b11111011 D
b101 B
1I
0J
b100 E
0'
1.
#1700000
0.
#1710000
b110 B
0I
1K
b11111011 C
b101 E
0b
1.
#1720000
0.
#1730000
b10 \
b101011 `
b111 B
1L
0K
b110 E
1'
1.
#1740000
0.
#1750000
b1000 B
0L
1J
b10 \
b101011 `
b111 E
1b
b101011 _
b10 Z
1.
#1760000
0.
#1770000
b11110111 D
b1001 B
1I
0J
b1000 E
0'
1.
#1780000
0.
#1790000
b1010 B
0I
1K
b11110111 C
b1001 E
0b
1.
#1800000
0.
#1810000
b11 \
b1010111 `
b1011 B
1L
0K
b1010 E
1'
1.
#1820000
0.
#1830000
b1100 B
0L
1J
b11 \
b1010111 `
b1011 E
1b
b1010111 _
b11 Z
1.
#1840000
0.
#1850000
b11101111 D
b1101 B
1I
0J
b1100 E
0'
1.
#1860000
0.
#1870000
b1110 B
0I
1K
b11101111 C
b1101 E
0b
1.
#1880000
0.
#1890000
b100 \
b10101111 `
b1111 B
1L
0K
b1110 E
1'
1.
#1900000
0.
#1910000
b10000 B
0L
1J
b100 \
b10101111 `
b1111 E
1b
b10101111 _
b100 Z
1.
#1920000
0.
#1930000
b11011111 D
b10001 B
1I
0J
b10000 E
0'
1.
#1940000
0.
#1950000
b10010 B
0I
1K
b11011111 C
b10001 E
0b
1.
#1960000
0.
#1970000
b101 \
b1011111 `
b10011 B
1L
0K
b10010 E
1'
1.
#1980000
0.
#1990000
b10100 B
0L
1J
b101 \
b1011111 `
b10011 E
1b
b1011111 _
b101 Z
1.
#2000000
0.
#2010000
b10111111 D
b10101 B
1I
0J
b10100 E
0'
1.
#2020000
0.
#2030000
b10110 B
0I
1K
b10111111 C
b10101 E
0b
1.
#2040000
0.
#2050000
b110 \
b10111111 `
b10111 B
1L
0K
b10110 E
1'
1.
#2060000
0.
#2070000
b11000 B
0L
1J
b110 \
b10111111 `
b10111 E
1b
b10111111 _
b110 Z
1.
#2080000
0.
#2090000
b1111111 D
b11001 B
1I
0J
b11000 E
0'
1.
#2100000
0.
#2110000
b11010 B
0I
1K
b1111111 C
b11001 E
0b
1.
#2120000
0.
#2130000
b111 \
b1111111 `
b11011 B
1L
0K
b11010 E
1'
1.
#2140000
0.
#2150000
b11100 B
0L
1J
b111 \
b1111111 `
b11011 E
1b
b1111111 _
b111 Z
1.
#2160000
0.
