src/i2c_generator.v
module i2c_generator (
    input          CLK,
    input          RST,      // RST=1 normal funstion, 0 restart

    // CPU
    input          RNW,
    input   [6:0]  I2C_ADDR,
    input   [15:0] WR_DATA, //write data from cpu to I2C
    output reg [15:0] RD_DATA, //read data from I2C to cpu
    input          START_STB,

    // I2C 
    output reg        SCL,
    output reg        SDA_OUT,
    output reg        SDA_OE,
    input         SDA_IN
);


    reg _nxt_sda_o;
    reg [4:0] _stage_count, _nxt_stage_count;
    reg [7:0] _shift, _shifted;
    reg [15:0]_nxt_rd_data;
  
    reg [11:0] _state, _next_state;
    localparam  IDLE        = 12'b1,
                START       = 12'b10,
                ADDR        = 12'b100,
                ACK         = 12'b1000,
                WRITE_HIGH  = 12'b10000,
                WRITE_ACK   = 12'b100000,
                WRITE_LOW   = 12'b1000000,
                WAIT_ACK    = 12'b10000000,
                READ_HIGH   = 12'b100000000,
                READ_ACK    = 12'b1000000000,
                READ_LOW    = 12'b10000000000,
                LAST_ACK    = 12'b100000000000;

    always @(*) begin
        SDA_OE = 1;
        _next_state = _state;
        _nxt_sda_o = SDA_OUT;  
        _shifted = _shift;
        _nxt_rd_data = RD_DATA;
        case (_state)
            IDLE: begin
                _nxt_stage_count = 5'b11111;
                _nxt_sda_o = 1;    
                if (START_STB) begin
                    _next_state = START;
                    _nxt_sda_o = 0;
                end
            end
            START: begin
                _nxt_stage_count = _stage_count +1;
                _nxt_sda_o = 0;  
                _next_state = ADDR;
                _shifted = {I2C_ADDR, RNW};
            end
            ADDR: begin
                _nxt_stage_count = _stage_count +1;
                if (_stage_count[1:0] == 2'b00)begin
                    _nxt_sda_o = _shift[7];
                    _shifted = {_shift[6:0], 1'b1};
                end
                if (_stage_count[4:0] == 5'b11111)begin
                    _next_state = ACK;
                end
            end
            ACK: begin
                _nxt_stage_count = _stage_count +1;
                if (_stage_count != 0) begin
                    SDA_OE = 0;
                    if (_stage_count[1:0] == 2'b10 && SDA_IN == 1) begin //if NACK
                        _next_state = IDLE; 
                        _nxt_sda_o = 1;    
                    end 
                    if (_stage_count[1:0] == 2'b11) begin
                        _next_state = (RNW)? READ_HIGH : WRITE_HIGH;
                        _nxt_stage_count = 5'b00000;
                        _shifted = WR_DATA[15:8];
                    end
                end
            end
            // ------------------------------------------------------------------WRITE LOGIC ---------------------------------------------------------------
            WRITE_HIGH: begin
                _nxt_stage_count = _stage_count +1;
                if (_stage_count == 0) SDA_OE = 0;
                if (_stage_count[1:0] == 2'b00)begin
                    _nxt_sda_o = _shift[7];
                    _shifted = {_shift[6:0], 1'b1};
                end
                if (_stage_count[4:0] == 5'b11111)begin
                    _next_state = WRITE_ACK;
                end
            end
            WRITE_ACK: begin
                _nxt_stage_count = _stage_count +1;
                if (_stage_count != 0) begin
                    SDA_OE = 0;
                    if (_stage_count[1:0] == 2'b10 && SDA_IN == 1) begin //if NACK
                        _next_state = IDLE; 
                        _nxt_sda_o = 1;    
                    end 
                    if (_stage_count[1:0] == 2'b11) begin
                        _next_state = WRITE_LOW;
                        _nxt_stage_count = 5'b00000;
                        _shifted = WR_DATA[7:0];
                    end
                end
            end
            WRITE_LOW: begin
                _nxt_stage_count = _stage_count +1;
                if (_stage_count == 0) SDA_OE = 0;
                if (_stage_count[1:0] == 2'b00)begin
                    _nxt_sda_o = _shift[7];
                    _shifted = {_shift[6:0], 1'b1};
                end
                if (_stage_count[4:0] == 5'b11111)begin
                    _next_state = WAIT_ACK;
                end
            end
            WAIT_ACK: begin
                _nxt_stage_count = _stage_count +1;
                if (_stage_count != 0) begin
                    if (_stage_count[2:0] != 3'd5 && _stage_count[2:0] != 3'd6) SDA_OE = 0; //exclude last two cycles
                    if (_stage_count[2:0] == 3'b110) begin 
                        _nxt_stage_count = 5'b11111;
                        _nxt_sda_o = 1;    
                        _next_state = IDLE;  //STOP
                    end 
                end
            end
            // ------------------------------------------------------------------READ LOGIC ---------------------------------------------------------------
            READ_HIGH: begin
                _nxt_stage_count = _stage_count +1;
                SDA_OE = 0;
                if (_stage_count[1:0] == 2'b10)begin
                    _shifted = {_shift[6:0], SDA_IN};
                end
                if (_stage_count[4:0] == 5'b11111)begin
                    _next_state = READ_ACK;
                end
            end
            READ_ACK: begin
                _nxt_sda_o = 0; //ACK 
                _nxt_rd_data = {_shift, 8'b0000000};
                _nxt_stage_count = _stage_count +1;
                if (_stage_count == 0) SDA_OE = 0;
                else begin
                    if (_stage_count[2:0] == 3'b100) begin // Extended one more cycle to keep SDA_OE enabled
                        _next_state = READ_LOW;
                        _nxt_stage_count = 5'b00001;
                    end
                end
            end            
            READ_LOW: begin
                SDA_OE = 0;
                _nxt_stage_count = _stage_count +1;
                SDA_OE = 0;
                if (_stage_count[1:0] == 2'b10)begin
                    _shifted = {_shift[6:0], SDA_IN};
                end
                if (_stage_count[4:0] == 5'b11111)begin
                    _next_state = LAST_ACK;
                end
            end
            LAST_ACK: begin
                _nxt_sda_o = 0; //ACK
                _nxt_rd_data = {RD_DATA[15:8], _shift};
                _nxt_stage_count = _stage_count +1;
                if (_stage_count == 0) SDA_OE = 0;
                else begin
                    if (_stage_count[2:0] == 3'b110) begin
                        _next_state = IDLE;
                        _nxt_stage_count = 5'b11111;
                        _nxt_sda_o = 1;    
                    end
                end
            end
        endcase
    end


    always @(posedge CLK or negedge RST) begin
        if (!RST) begin
            //reset
            _state <= IDLE;
            SDA_OUT <= 1'b1;
            SCL <= 1'b1;
            SDA_OE <= 1'b0;
            _stage_count <= 5'b0;
            _shift <= 8'b0;
        end else begin
            // not a reset
            _state <= _next_state;
            SDA_OUT <= _nxt_sda_o;
            SCL <= _nxt_stage_count[1];
            _stage_count <= _nxt_stage_count;
            _shift <= _shifted;
            RD_DATA <= _nxt_rd_data;
        end
    end

endmodule

sim/tester.v
`timescale 1ns / 1ps

module tester (
    // Outputs to the DUT (CPU Side)
    output reg         CLK,
    output reg         RST,
    output reg         RNW,
    output reg [6:0]   I2C_ADDR,
    output reg [15:0]  WR_DATA,
    output reg         START_STB,
    
    // Inputs from the DUT (CPU Side)
    input      [15:0]  RD_DATA,

    // Interfacing with the I2C physical line
    input              SCL,
    input              SDA_OUT,
    input              SDA_OE,
    output reg         SDA_IN
);

    // Clock generation (50MHz)
    always #10 CLK = ~CLK;

    // Monitor I2C state changes & emulate Slave Behavior
    initial begin
        // Initialize lines
        CLK = 0;
        RST = 0;
        RNW = 0;
        I2C_ADDR = 7'h00;
        WR_DATA = 16'h0000;
        START_STB = 0;
        SDA_IN = 1; // Pull-up default

        // Release Reset
        #40;
        RST = 1;
        #20;

        // ==========================================
        // TEST CASE 1: Write Operation (Address 0x50, Data 0xA53C)
        // ==========================================
        $display("[TEST] Starting I2C Write transaction...");
        I2C_ADDR  = 7'h50; 
        WR_DATA   = 16'hA53C;
        RNW       = 1'b0; // Write
        START_STB = 1'b1;

        $display("sending ADDR");
        repeat(8) @(posedge SCL);
        START_STB = 1'b0;


        $display("Slave ADDR ACK");
        // Drive ACK during the 9th clock cycle low period
        @(negedge SCL);
        SDA_IN = 1'b0; // Send ACK
        @(negedge SCL);
        SDA_IN = 1'b1; // Release

        $display("sending high byte: ");
        // Emulate Data High Byte ACK (0xA5)
        repeat(8) @(posedge SCL);


        $display("Slave HIGH ACK");
        @(negedge SCL);
        SDA_IN = 1'b0; // Send ACK
        @(negedge SCL);
        SDA_IN = 1'b1; // Release


         $display("sending low byte: ");
        // Emulate Data Low Byte ACK (0x3C)
        repeat(8) @(posedge SCL);

        @(negedge SCL);
        SDA_IN = 1'b0; // Send ACK
        @(posedge SCL);
        SDA_IN = 1'b1; // Release

        $display("sent ");
        #200;

        // ==========================================
        // TEST CASE 2: Read Operation (Address 0x2A, Expecting Data 0x55E0)
        // ==========================================
        $display("[TEST] Starting I2C Read transaction...");
        I2C_ADDR  = 7'h2A;
        RNW       = 1'b1; // Read
        START_STB = 1'b1;


        $display("sending ADDR");
        repeat(8) @(posedge SCL);
        START_STB = 1'b0;


        $display("Slave ADDR ACK");
        // Drive ACK during the 9th clock cycle low period
        @(negedge SCL);
        SDA_IN = 1'b0; // Send ACK
        @(negedge SCL);
        SDA_IN = 1'b1; // Release
        
        $display("Sending byte");
        // Emulate providing Data Byte High (0x55 -> 01010101)
        // Bit 7
        @(negedge SCL); SDA_IN = 0; @(negedge SCL); SDA_IN = 1;
        // Bit 5
        @(negedge SCL); SDA_IN = 0; @(negedge SCL); SDA_IN = 1;
        // Bit 3
        @(negedge SCL); SDA_IN = 0; @(negedge SCL); SDA_IN = 1;
        // Bit 1
        @(negedge SCL); SDA_IN = 0; @(negedge SCL); 
        SDA_IN = 1'b1; // Release for DUT Master ACK

        $display("Waiting for Master ACK");
        // Wait for Master ACK
        @(posedge SCL); 

        // Emulate providing Data Byte Low (0xE0 -> 11100000)
        @(negedge SCL); SDA_IN = 1;
        @(negedge SCL); SDA_IN = 1;
        @(negedge SCL); SDA_IN = 1;
        @(negedge SCL); SDA_IN = 0;
        @(negedge SCL); SDA_IN = 0;
        @(negedge SCL); SDA_IN = 0;
        @(negedge SCL); SDA_IN = 0;
        @(negedge SCL); SDA_IN = 0;
        
        @(negedge SCL);
        SDA_IN = 1'b1; // Release for Master Last ACK

        repeat(8) @(posedge CLK);
        $display("[TEST] Transactions finished. Checking Read Data: %h", RD_DATA);

        $finish; 
    end

endmodule

sim/master_testbench.v
//`include "build/i2c_generator_synth.v" // Archivo generado por Yosys

`include "syn/cmos_cells.v"    // Celdas de la biblioteca para simulación


`include "src/i2c_generator.v"
`include "sim/master_tester.v"


`timescale 1ns / 1ps

module tb_i2c_generator();

    // Interconnect wires (CPU Side)
    wire        clk;
    wire        rst;
    wire        rnw;
    wire [6:0]  i2c_addr;
    wire [15:0] wr_data;
    wire        start_stb;
    wire [15:0] rd_data;

    // Interconnect wires (I2C Physical Side)
    wire        scl;
    wire        sda_out;
    wire        sda_oe;
    wire        sda_in;
    

    // Instantiate the Tester Module
    tester u_tester (
        .CLK(clk),
        .RST(rst),
        .RNW(rnw),
        .I2C_ADDR(i2c_addr),
        .WR_DATA(wr_data),
        .START_STB(start_stb),
        .RD_DATA(rd_data),
        .SCL(scl),
        .SDA_OUT(sda_out),
        .SDA_OE(sda_oe),
        .SDA_IN(sda_in)
    );

    // Instantiate the Design Under Test (DUT)
    i2c_generator dut (
        .CLK(clk),
        .RST(rst),
        .RNW(rnw),
        .I2C_ADDR(i2c_addr),
        .WR_DATA(wr_data),
        .RD_DATA(rd_data),
        .START_STB(start_stb),
        .SCL(scl),
        .SDA_OUT(sda_out),
        .SDA_OE(sda_oe),
        .SDA_IN(sda_in) // Inout resolution handling inside the system
    );

    // Waveform setup for visualization
    initial begin
        $dumpfile("i2c_simulation.vcd");
        $dumpvars(0, tb_i2c_generator);
    end

endmodule

i2c_simulation.vcd
$date
	Fri Jun  5 15:40:41 2026
$end
$version
	Icarus Verilog
$end
$timescale
	1ps
$end
$scope module tb_i2c_generator $end
$var wire 16 ! wr_data [15:0] $end
$var wire 1 " start_stb $end
$var wire 1 # sda_out $end
$var wire 1 $ sda_oe $end
$var wire 1 % sda_in $end
$var wire 1 & scl $end
$var wire 1 ' rst $end
$var wire 1 ( rnw $end
$var wire 16 ) rd_data [15:0] $end
$var wire 7 * i2c_addr [6:0] $end
$var wire 1 + clk $end
$scope module dut $end
$var wire 16 , WR_DATA [15:0] $end
$var wire 1 " START_STB $end
$var wire 1 % SDA_IN $end
$var wire 1 ' RST $end
$var wire 1 ( RNW $end
$var wire 7 - I2C_ADDR [6:0] $end
$var wire 1 + CLK $end
$var parameter 12 . ACK $end
$var parameter 12 / ADDR $end
$var parameter 12 0 IDLE $end
$var parameter 12 1 LAST_ACK $end
$var parameter 12 2 READ_ACK $end
$var parameter 12 3 READ_HIGH $end
$var parameter 12 4 READ_LOW $end
$var parameter 12 5 START $end
$var parameter 12 6 WAIT_ACK $end
$var parameter 12 7 WRITE_ACK $end
$var parameter 12 8 WRITE_HIGH $end
$var parameter 12 9 WRITE_LOW $end
$var reg 16 : RD_DATA [15:0] $end
$var reg 1 & SCL $end
$var reg 1 $ SDA_OE $end
$var reg 1 # SDA_OUT $end
$var reg 12 ; _next_state [11:0] $end
$var reg 16 < _nxt_rd_data [15:0] $end
$var reg 1 = _nxt_sda_o $end
$var reg 5 > _nxt_stage_count [4:0] $end
$var reg 8 ? _shift [7:0] $end
$var reg 8 @ _shifted [7:0] $end
$var reg 5 A _stage_count [4:0] $end
$var reg 12 B _state [11:0] $end
$upscope $end
$scope module u_tester $end
$var wire 16 C RD_DATA [15:0] $end
$var wire 1 & SCL $end
$var wire 1 $ SDA_OE $end
$var wire 1 # SDA_OUT $end
$var reg 1 + CLK $end
$var reg 7 D I2C_ADDR [6:0] $end
$var reg 1 ( RNW $end
$var reg 1 ' RST $end
$var reg 1 % SDA_IN $end
$var reg 1 " START_STB $end
$var reg 16 E WR_DATA [15:0] $end
$upscope $end
$upscope $end
$enddefinitions $end
$comment Show the parameter values. $end
$dumpall
b1000000 9
b10000 8
b100000 7
b10000000 6
b10 5
b10000000000 4
b100000000 3
b1000000000 2
b100000000000 1
b1 0
b100 /
b1000 .
$end
#0
$dumpvars
b0 E
b0 D
bx C
bx B
bx A
bx @
bx ?
bx >
x=
bx <
bx ;
bx :
b0 -
b0 ,
0+
b0 *
bx )
0(
0'
x&
1%
1$
x#
0"
b0 !
$end
#10000
b11111 >
b0 @
1=
b1 ;
b0 ?
b0 A
1$
1&
1#
b1 B
1+
#20000
0+
#30000
0$
1+
#40000
0+
1'
#50000
1$
b11111 A
1+
#60000
0=
b10 ;
0+
1"
b1010010100111100 !
b1010010100111100 ,
b1010010100111100 E
b1010000 *
b1010000 -
b1010000 D
#70000
b10100000 @
b100 ;
b0 >
0#
b10 B
1+
#80000
0+
#90000
b1000001 @
1=
b1 >
b10100000 ?
b0 A
0&
b100 B
1+
#100000
0+
#110000
b10 >
b1000001 ?
b1 A
1#
1+
#120000
0+
#130000
b11 >
b10 A
1&
1+
#140000
0+
#150000
b100 >
b11 A
1+
#160000
0+
#170000
b10000011 @
0=
b101 >
b100 A
0&
1+
#180000
0+
#190000
b110 >
b10000011 ?
b101 A
0#
1+
#200000
0+
#210000
b111 >
b110 A
1&
1+
#220000
0+
#230000
b1000 >
b111 A
1+
#240000
0+
#250000
b111 @
1=
b1001 >
b1000 A
0&
1+
#260000
0+
#270000
b1010 >
b111 ?
b1001 A
1#
1+
#280000
0+
#290000
b1011 >
b1010 A
1&
1+
#300000
0+
#310000
b1100 >
b1011 A
1+
#320000
0+
#330000
b1111 @
0=
b1101 >
b1100 A
0&
1+
#340000
0+
#350000
b1110 >
b1111 ?
b1101 A
0#
1+
#360000
0+
#370000
b1111 >
b1110 A
1&
1+
#380000
0+
#390000
b10000 >
b1111 A
1+
#400000
0+
#410000
b11111 @
b10001 >
b10000 A
0&
1+
#420000
0+
#430000
b10010 >
b11111 ?
b10001 A
1+
#440000
0+
#450000
b10011 >
b10010 A
1&
1+
#460000
0+
#470000
b10100 >
b10011 A
1+
#480000
0+
#490000
b111111 @
b10101 >
b10100 A
0&
1+
#500000
0+
#510000
b10110 >
b111111 ?
b10101 A
1+
#520000
0+
#530000
b10111 >
b10110 A
1&
1+
#540000
0+
#550000
b11000 >
b10111 A
1+
#560000
0+
#570000
b1111111 @
b11001 >
b11000 A
0&
1+
#580000
0+
#590000
b11010 >
b1111111 ?
b11001 A
1+
#600000
0+
#610000
b11011 >
b11010 A
1&
1+
#620000
0+
#630000
b11100 >
b11011 A
1+
#640000
0+
#650000
b11111111 @
b11101 >
b11100 A
0&
1+
#660000
0+
#670000
b11110 >
b11111111 ?
b11101 A
1+
#680000
0+
#690000
b11111 >
0"
b11110 A
1&
1+
#700000
0+
#710000
b1000 ;
b0 >
b11111 A
1+
#720000
0+
#730000
0%
b1 >
b0 A
0&
b1000 B
1+
#740000
0+
#750000
0$
b10 >
b1 A
1+
#760000
0+
#770000
b11 >
0$
b10 A
1&
1+
#780000
0+
#790000
b10100101 @
b10000 ;
b0 >
0$
b11 A
1+
#800000
0+
#810000
1%
b1001011 @
1=
b1 >
0$
b10100101 ?
b0 A
0&
b10000 B
1+
#820000
0+
#830000
b10 >
1$
b1001011 ?
b1 A
1#
1+
#840000
0+
#850000
b11 >
b10 A
1&
1+
#860000
0+
#870000
b100 >
b11 A
1+
#880000
0+
#890000
b10010111 @
0=
b101 >
b100 A
0&
1+
#900000
0+
#910000
b110 >
b10010111 ?
b101 A
0#
1+
#920000
0+
#930000
b111 >
b110 A
1&
1+
#940000
0+
#950000
b1000 >
b111 A
1+
#960000
0+
#970000
b101111 @
1=
b1001 >
b1000 A
0&
1+
#980000
0+
#990000
b1010 >
b101111 ?
b1001 A
1#
1+
#1000000
0+
#1010000
b1011 >
b1010 A
1&
1+
#1020000
0+
#1030000
b1100 >
b1011 A
1+
#1040000
0+
#1050000
b1011111 @
0=
b1101 >
b1100 A
0&
1+
#1060000
0+
#1070000
b1110 >
b1011111 ?
b1101 A
0#
1+
#1080000
0+
#1090000
b1111 >
b1110 A
1&
1+
#1100000
0+
#1110000
b10000 >
b1111 A
1+
#1120000
0+
#1130000
b10111111 @
b10001 >
b10000 A
0&
1+
#1140000
0+
#1150000
b10010 >
b10111111 ?
b10001 A
1+
#1160000
0+
#1170000
b10011 >
b10010 A
1&
1+
#1180000
0+
#1190000
b10100 >
b10011 A
1+
#1200000
0+
#1210000
b1111111 @
1=
b10101 >
b10100 A
0&
1+
#1220000
0+
#1230000
b10110 >
b1111111 ?
b10101 A
1#
1+
#1240000
0+
#1250000
b10111 >
b10110 A
1&
1+
#1260000
0+
#1270000
b11000 >
b10111 A
1+
#1280000
0+
#1290000
b11111111 @
0=
b11001 >
b11000 A
0&
1+
#1300000
0+
#1310000
b11010 >
b11111111 ?
b11001 A
0#
1+
#1320000
0+
#1330000
b11011 >
b11010 A
1&
1+
#1340000
0+
#1350000
b11100 >
b11011 A
1+
#1360000
0+
#1370000
1=
b11101 >
b11100 A
0&
1+
#1380000
0+
#1390000
b11110 >
b11101 A
1#
1+
#1400000
0+
#1410000
b11111 >
b11110 A
1&
1+
#1420000
0+
#1430000
b100000 ;
b0 >
b11111 A
1+
#1440000
0+
#1450000
0%
b1 >
b0 A
0&
b100000 B
1+
#1460000
0+
#1470000
0$
b10 >
b1 A
1+
#1480000
0+
#1490000
b11 >
0$
b10 A
1&
1+
#1500000
0+
#1510000
b111100 @
b1000000 ;
b0 >
0$
b11 A
1+
#1520000
0+
#1530000
1%
b1111001 @
0=
b1 >
0$
b111100 ?
b0 A
0&
b1000000 B
1+
#1540000
0+
#1550000
b10 >
1$
b1111001 ?
b1 A
0#
1+
#1560000
0+
#1570000
b11 >
b10 A
1&
1+
#1580000
0+
#1590000
b100 >
b11 A
1+
#1600000
0+
#1610000
b11110011 @
b101 >
b100 A
0&
1+
#1620000
0+
#1630000
b110 >
b11110011 ?
b101 A
1+
#1640000
0+
#1650000
b111 >
b110 A
1&
1+
#1660000
0+
#1670000
b1000 >
b111 A
1+
#1680000
0+
#1690000
b11100111 @
1=
b1001 >
b1000 A
0&
1+
#1700000
0+
#1710000
b1010 >
b11100111 ?
b1001 A
1#
1+
#1720000
0+
#1730000
b1011 >
b1010 A
1&
1+
#1740000
0+
#1750000
b1100 >
b1011 A
1+
#1760000
0+
#1770000
b11001111 @
b1101 >
b1100 A
0&
1+
#1780000
0+
#1790000
b1110 >
b11001111 ?
b1101 A
1+
#1800000
0+
#1810000
b1111 >
b1110 A
1&
1+
#1820000
0+
#1830000
b10000 >
b1111 A
1+
#1840000
0+
#1850000
b10011111 @
b10001 >
b10000 A
0&
1+
#1860000
0+
#1870000
b10010 >
b10011111 ?
b10001 A
1+
#1880000
0+
#1890000
b10011 >
b10010 A
1&
1+
#1900000
0+
#1910000
b10100 >
b10011 A
1+
#1920000
0+
#1930000
b111111 @
b10101 >
b10100 A
0&
1+
#1940000
0+
#1950000
b10110 >
b111111 ?
b10101 A
1+
#1960000
0+
#1970000
b10111 >
b10110 A
1&
1+
#1980000
0+
#1990000
b11000 >
b10111 A
1+
#2000000
0+
#2010000
b1111111 @
0=
b11001 >
b11000 A
0&
1+
#2020000
0+
#2030000
b11010 >
b1111111 ?
b11001 A
0#
1+
#2040000
0+
#2050000
b11011 >
b11010 A
1&
1+
#2060000
0+
#2070000
b11100 >
b11011 A
1+
#2080000
0+
#2090000
b11111111 @
b11101 >
b11100 A
0&
1+
#2100000
0+
#2110000
b11110 >
b11111111 ?
b11101 A
1+
#2120000
0+
#2130000
b11111 >
b11110 A
1&
1+
#2140000
0+
#2150000
b10000000 ;
b0 >
b11111 A
1+
#2160000
0+
#2170000
0%
b1 >
b0 A
0&
b10000000 B
1+
#2180000
0+
#2190000
0$
b10 >
b1 A
1+
#2200000
0+
#2210000
b11 >
0$
1%
b10 A
1&
1+
#2220000
0+
#2230000
b100 >
0$
b11 A
1+
#2240000
0+
#2250000
b101 >
0$
b100 A
0&
1+
#2260000
0+
#2270000
b110 >
1$
b101 A
1+
#2280000
0+
#2290000
b1 ;
1=
b11111 >
b110 A
1&
1+
#2300000
0+
#2310000
b11111 A
1#
b1 B
1+
#2320000
0+
#2330000
1+
#2340000
0+
#2350000
1+
#2360000
0+
#2370000
1+
#2380000
0+
#2390000
1+
#2400000
0+
#2410000
b1010101 @
b0 >
0#
b10 B
0=
b100 ;
1+
1"
1(
b101010 *
b101010 -
b101010 D
#2420000
0+
#2430000
b10101011 @
b1 >
b1010101 ?
b0 A
0&
b100 B
1+
#2440000
0+
#2450000
b10 >
b10101011 ?
b1 A
1+
#2460000
0+
#2470000
b11 >
b10 A
1&
1+
#2480000
0+
#2490000
b100 >
b11 A
1+
#2500000
0+
#2510000
b1010111 @
1=
b101 >
b100 A
0&
1+
#2520000
0+
#2530000
b110 >
b1010111 ?
b101 A
1#
1+
#2540000
0+
#2550000
b111 >
b110 A
1&
1+
#2560000
0+
#2570000
b1000 >
b111 A
1+
#2580000
0+
#2590000
b10101111 @
0=
b1001 >
b1000 A
0&
1+
#2600000
0+
#2610000
b1010 >
b10101111 ?
b1001 A
0#
1+
#2620000
0+
#2630000
b1011 >
b1010 A
1&
1+
#2640000
0+
#2650000
b1100 >
b1011 A
1+
#2660000
0+
#2670000
b1011111 @
1=
b1101 >
b1100 A
0&
1+
#2680000
0+
#2690000
b1110 >
b1011111 ?
b1101 A
1#
1+
#2700000
0+
#2710000
b1111 >
b1110 A
1&
1+
#2720000
0+
#2730000
b10000 >
b1111 A
1+
#2740000
0+
#2750000
b10111111 @
0=
b10001 >
b10000 A
0&
1+
#2760000
0+
#2770000
b10010 >
b10111111 ?
b10001 A
0#
1+
#2780000
0+
#2790000
b10011 >
b10010 A
1&
1+
#2800000
0+
#2810000
b10100 >
b10011 A
1+
#2820000
0+
#2830000
b1111111 @
1=
b10101 >
b10100 A
0&
1+
#2840000
0+
#2850000
b10110 >
b1111111 ?
b10101 A
1#
1+
#2860000
0+
#2870000
b10111 >
b10110 A
1&
1+
#2880000
0+
#2890000
b11000 >
b10111 A
1+
#2900000
0+
#2910000
b11111111 @
0=
b11001 >
b11000 A
0&
1+
#2920000
0+
#2930000
b11010 >
b11111111 ?
b11001 A
0#
1+
#2940000
0+
#2950000
b11011 >
b11010 A
1&
1+
#2960000
0+
#2970000
b11100 >
b11011 A
1+
#2980000
0+
#2990000
1=
b11101 >
b11100 A
0&
1+
#3000000
0+
#3010000
b11110 >
b11101 A
1#
1+
#3020000
0+
#3030000
b11111 >
0"
b11110 A
1&
1+
#3040000
0+
#3050000
b1000 ;
b0 >
b11111 A
1+
#3060000
0+
#3070000
0%
b1 >
b0 A
0&
b1000 B
1+
#3080000
0+
#3090000
0$
b10 >
b1 A
1+
#3100000
0+
#3110000
b11 >
0$
b10 A
1&
1+
#3120000
0+
#3130000
b10100101 @
b100000000 ;
b0 >
0$
b11 A
1+
#3140000
0+
#3150000
1%
b1 >
0$
b10100101 ?
b0 A
0&
b100000000 B
1+
#3160000
0+
#3170000
b10 >
0$
b1 A
1+
#3180000
0+
#3190000
b1001011 @
b11 >
0$
b10 A
1&
1+
#3200000
0+
#3210000
b100 >
0$
b1001011 ?
b11 A
1+
#3220000
0+
#3230000
b101 >
0$
0%
b100 A
0&
1+
#3240000
0+
#3250000
b110 >
0$
b101 A
1+
#3260000
0+
#3270000
b10010110 @
b111 >
0$
b110 A
1&
1+
#3280000
0+
#3290000
b1000 >
0$
b10010110 ?
b111 A
1+
#3300000
0+
#3310000
b1001 >
0$
1%
b1000 A
0&
1+
#3320000
0+
#3330000
b1010 >
0$
b1001 A
1+
#3340000
0+
#3350000
b101101 @
b1011 >
0$
b1010 A
1&
1+
#3360000
0+
#3370000
b1100 >
0$
b101101 ?
b1011 A
1+
#3380000
0+
#3390000
b1101 >
0$
0%
b1100 A
0&
1+
#3400000
0+
#3410000
b1110 >
0$
b1101 A
1+
#3420000
0+
#3430000
b1011010 @
b1111 >
0$
b1110 A
1&
1+
#3440000
0+
#3450000
b10000 >
0$
b1011010 ?
b1111 A
1+
#3460000
0+
#3470000
b10001 >
0$
1%
b10000 A
0&
1+
#3480000
0+
#3490000
b10010 >
0$
b10001 A
1+
#3500000
0+
#3510000
b10110101 @
b10011 >
0$
b10010 A
1&
1+
#3520000
0+
#3530000
b10100 >
0$
b10110101 ?
b10011 A
1+
#3540000
0+
#3550000
b10101 >
0$
0%
b10100 A
0&
1+
#3560000
0+
#3570000
b10110 >
0$
b10101 A
1+
#3580000
0+
#3590000
b1101010 @
b10111 >
0$
b10110 A
1&
1+
#3600000
0+
#3610000
b11000 >
0$
b1101010 ?
b10111 A
1+
#3620000
0+
#3630000
b11001 >
0$
1%
b11000 A
0&
1+
#3640000
0+
#3650000
b11010 >
0$
b11001 A
1+
#3660000
0+
#3670000
b11010101 @
b11011 >
0$
b11010 A
1&
1+
#3680000
0+
#3690000
b11100 >
0$
b11010101 ?
b11011 A
1+
#3700000
0+
#3710000
b11101 >
0$
0%
b11100 A
0&
1+
#3720000
0+
#3730000
b11110 >
0$
b11101 A
1+
#3740000
0+
#3750000
b10101010 @
b11111 >
0$
b11110 A
1&
1+
#3760000
0+
#3770000
b1000000000 ;
b0 >
0$
b10101010 ?
b11111 A
1+
#3780000
0+
#3790000
1%
b1 >
b1010101000000000 <
0=
0$
b0 A
0&
b1000000000 B
1+
#3800000
0+
#3810000
b10 >
1$
b1010101000000000 )
b1010101000000000 :
b1010101000000000 C
b1 A
0#
1+
#3820000
0+
#3830000
b11 >
b10 A
1&
1+
#3840000
0+
#3850000
b100 >
b11 A
1+
#3860000
0+
#3870000
b10000000000 ;
b1 >
b100 A
0&
1+
#3880000
0+
#3890000
b10 >
0$
b1 A
b10000000000 B
1+
#3900000
0+
#3910000
b1010101 @
b11 >
0$
b10 A
1&
1+
#3920000
0+
#3930000
b100 >
0$
b1010101 ?
b11 A
1+
#3940000
0+
#3950000
b101 >
0$
b100 A
0&
1+
#3960000
0+
#3970000
b110 >
0$
b101 A
1+
#3980000
0+
#3990000
b10101011 @
b111 >
0$
b110 A
1&
1+
#4000000
0+
#4010000
b1000 >
0$
b10101011 ?
b111 A
1+
#4020000
0+
#4030000
b1001 >
0$
b1000 A
0&
1+
#4040000
0+
#4050000
b1010 >
0$
b1001 A
1+
#4060000
0+
#4070000
b1010111 @
b1011 >
0$
b1010 A
1&
1+
#4080000
0+
#4090000
b1100 >
0$
b1010111 ?
b1011 A
1+
#4100000
0+
#4110000
b1101 >
0$
0%
b1100 A
0&
1+
#4120000
0+
#4130000
b1110 >
0$
b1101 A
1+
#4140000
0+
#4150000
b10101110 @
b1111 >
0$
b1110 A
1&
1+
#4160000
0+
#4170000
b10000 >
0$
b10101110 ?
b1111 A
1+
#4180000
0+
#4190000
b10001 >
0$
b10000 A
0&
1+
#4200000
0+
#4210000
b10010 >
0$
b10001 A
1+
#4220000
0+
#4230000
b1011100 @
b10011 >
0$
b10010 A
1&
1+
#4240000
0+
#4250000
b10100 >
0$
b1011100 ?
b10011 A
1+
#4260000
0+
#4270000
b10101 >
0$
b10100 A
0&
1+
#4280000
0+
#4290000
b10110 >
0$
b10101 A
1+
#4300000
0+
#4310000
b10111000 @
b10111 >
0$
b10110 A
1&
1+
#4320000
0+
#4330000
b11000 >
0$
b10111000 ?
b10111 A
1+
#4340000
0+
#4350000
b11001 >
0$
b11000 A
0&
1+
#4360000
0+
#4370000
b11010 >
0$
b11001 A
1+
#4380000
0+
#4390000
b1110000 @
b11011 >
0$
b11010 A
1&
1+
#4400000
0+
#4410000
b11100 >
0$
b1110000 ?
b11011 A
1+
#4420000
0+
#4430000
b11101 >
0$
b11100 A
0&
1+
#4440000
0+
#4450000
b11110 >
0$
b11101 A
1+
#4460000
0+
#4470000
b11100000 @
b11111 >
0$
b11110 A
1&
1+
#4480000
0+
#4490000
b100000000000 ;
b0 >
0$
b11100000 ?
b11111 A
1+
#4500000
0+
#4510000
1%
b1 >
b1010101011100000 <
0$
b0 A
0&
b100000000000 B
1+
#4520000
0+
#4530000
b10 >
1$
b1010101011100000 )
b1010101011100000 :
b1010101011100000 C
b1 A
1+
#4540000
0+
#4550000
b11 >
b10 A
1&
1+
#4560000
0+
#4570000
b100 >
b11 A
1+
#4580000
0+
#4590000
b101 >
b100 A
0&
1+
#4600000
0+
#4610000
b110 >
b101 A
1+
#4620000
0+
#4630000
1=
b1 ;
b11111 >
b110 A
1&
1+
#4640000
0+
#4650000
b11111 A
1#
b1 B
1+
